Workbook
Name \a: #REF!
Name \a: #REF!
Name \b: #REF!
Name \b: #REF!
Name \c: #REF!
Name \c: #REF!
Name \n: #REF!
Name \n: #REF!
Name \o: #REF!
Name \o: #REF!
Name _01: [1]Presupuesto!#REF!
Name _01: [1]Presupuesto!#REF!
Name _02: [1]Presupuesto!#REF!
Name _02: [1]Presupuesto!#REF!
Name _03: [1]Presupuesto!#REF!
Name _03: [1]Presupuesto!#REF!
Name _04: [1]Presupuesto!#REF!
Name _04: [1]Presupuesto!#REF!
Name _05: [1]Presupuesto!#REF!
Name _05: [1]Presupuesto!#REF!
Name _06: [1]Presupuesto!#REF!
Name _06: [1]Presupuesto!#REF!
Name _07: [1]Presupuesto!#REF!
Name _07: [1]Presupuesto!#REF!
Name _08: [1]Presupuesto!#REF!
Name _08: [1]Presupuesto!#REF!
Name _09: [1]Presupuesto!#REF!
Name _09: [1]Presupuesto!#REF!
Name _10: [1]Presupuesto!#REF!
Name _10: [1]Presupuesto!#REF!
Name _11: [1]Presupuesto!#REF!
Name _11: [1]Presupuesto!#REF!
Name _12: [1]Presupuesto!#REF!
Name _12: [1]Presupuesto!#REF!
Name _13: [1]Presupuesto!#REF!
Name _13: [1]Presupuesto!#REF!
Name _14: [1]Presupuesto!#REF!
Name _14: [1]Presupuesto!#REF!
Name _15: [1]Presupuesto!#REF!
Name _15: [1]Presupuesto!#REF!
Name _16: [1]Presupuesto!#REF!
Name _16: [1]Presupuesto!#REF!
Name _17: [1]Presupuesto!#REF!
Name _17: [1]Presupuesto!#REF!
Name _18: [1]Presupuesto!#REF!
Name _18: [1]Presupuesto!#REF!
Name _19: [1]Presupuesto!#REF!
Name _19: [1]Presupuesto!#REF!
Name _20: [1]Presupuesto!#REF!
Name _20: [1]Presupuesto!#REF!
Name _21: [1]Presupuesto!#REF!
Name _21: [1]Presupuesto!#REF!
Name _22: [1]Presupuesto!#REF!
Name _22: [1]Presupuesto!#REF!
Name _23: [1]Presupuesto!#REF!
Name _23: [1]Presupuesto!#REF!
Name _24: [1]Presupuesto!#REF!
Name _24: [1]Presupuesto!#REF!
Name _25: [1]Presupuesto!#REF!
Name _25: [1]Presupuesto!#REF!

Sheet PPTO ESTUDIO TV
BL2: PRESUPUESTO RESUMEN | BP2: =+$M$128 -> 1.588966
I3: SUP CUB. | J3: =SUM(J1:J2) -> 0 | BL3: ESTUDIO TV
P4: 1 - TRABAJOS PREPARATORIOS | X4: 4 - ESTRUCTURA RESISTENTE | AF4: 5 - MAMPOSTERIA | AN4: 10 - TABIQUE DE PLACAS DE YESO | AW4: 15 - INSTALACIÓN ELECTROMECÁNICA | BD4: 18 - VARIOS | BL4: LOCALIDAD: RESISTENCIA
E5: ESTUDIO TV | P5: 1.1 - TRASLADO DE MUEBLES, CUADROS, PAPELERIA, ETC | T5: =$G$13 -> Gl | U5: =$H$13 -> 1 | X5: 4.1.1 - HºAº PARA BASE ASCENSOR - H30 | AB5: =$G$27 -> m3 | AC5: =$H$27 -> 1.878225 | AF5: 5.1 - MAMP. ELEVACION LAD.COMUN - 0,18 | AJ5: =$G$41 -> m3 | AK5: =$H$41 -> 35.11 | AN5: 10.1 - TABIQUE DE PLACA DE YESO - DOBLE PLACA, LANA DE VIDRIO 70mm-ESTUDIO | AR5: =$G$59 -> m2 | AS5: =$H$59 -> 358.7 | AW5: 15.1 - ASCENSOR | BA5: =$G$101 -> Gl | BB5: =$H$101 -> 1 | BD5: 18.1 - LIMPIEZA DE OBRA | BH5: =$G$112 -> Gl | BI5: =$H$112 -> 1 | BL5: EMPRESA: I.L.A.G. CONSTRUCCIONES
E6: LOCALIDAD: RESISTENCIA
E7: EMPRESA: I.L.A.G. CONSTRUCCIONES | P7: DESCRIPCION | Q7: UNIDAD | R7: CANTIDAD | S7: PRECIO | T7: Subtotal | U7: FLETE | X7: DESCRIPCION | Y7: UNIDAD | Z7: CANTIDAD | AA7: PRECIO | AB7: Subtotal | AC7: FLETE | AF7: DESCRIPCION | AG7: UNIDAD | AH7: CANTIDAD | AI7: PRECIO | AJ7: Subtotal | AK7: FLETE | AN7: DESCRIPCION | AO7: UNIDAD | AP7: CANTIDAD | AQ7: PRECIO | AR7: Subtotal | AS7: FLETE | AW7: DESCRIPCION | AX7: UNIDAD | AY7: CANTIDAD | AZ7: PRECIO | BA7: Subtotal | BB7: FLETE | BD7: DESCRIPCION | BE7: UNIDAD | BF7: CANTIDAD | BG7: PRECIO | BH7: Subtotal | BI7: FLETE | BL7: Nº DE | BM7: DESIGNACION DE LA OBRA | BN7: PRECIO TOTAL | BO7: INCIDENCIA
E8: COMPUTO Y PRESUPUESTO | P8: Materiales: | X8: Materiales: | AF8: Materiales: | AN8: Materiales: | AW8: Materiales: | BD8: Materiales: | BL8: ITEMS | BO8: % TOTAL
T9: =+ROUND(R9*S9,2) -> 0 | X9: Hormigón Elaborado H-30 | Y9: m3 | Z9: 1.1 | AA9: 27425 | AB9: =+ROUND(Z9*AA9,2) -> 30167.5 | AF9: Ladrillos Comunes | AG9: Un | AH9: 290 | AI9: 37.45 | AJ9: =+ROUND(AH9*AI9,2) -> 10860.5 | AN9: TABIQUE DE PLACA DE YESO - DOBLE PLACA, LANA DE VIDRIO 70mm-ESTUDIO | AO9: m2 | AP9: 1.05 | AQ9: 31126.3 | AR9: =+ROUND(AP9*AQ9,2) -> 32682.62 | AW9: ASCENSOR HIDRAULICO LATERAL R PARADAS | AX9: GL | AY9: 1 | AZ9: 13504596 | BA9: =+ROUND(AY9*AZ9,2) -> 13504596 | BH9: =ROUND((BG9*BF9),2) -> 0
E10: RUBRO | F10: DESCRIPCION | G10: UN | H10: CANTIDAD | I10: COSTO UNIT | J10: COSTO ITEM | K10: TOTAL RUBRO | L10: % INCIDENCIA | T10: =+ROUND(R10*S10,2) -> 0 | X10: Hierro | Y10: Kg | Z10: 120 | AA10: 390.35069 | AB10: =+ROUND(Z10*AA10,2) -> 46842.08 | AF10: Cemento | AG10: Kg | AH10: 90 | AI10: 26.528938 | AJ10: =+ROUND(AH10*AI10,2) -> 2387.6 | AN10: Varios, carga, descarga y desperdicio | AO10: gl | AP10: 0.03 | AQ10: 32682.62 | AR10: =+ROUND(AP10*AQ10,2) -> 980.48 | AW10: VARIOS CONEXIONADO | AX10: GL | AY10: 1 | AZ10: 94532.172 | BA10: =+ROUND(AY10*AZ10,2) -> 94532.17 | BH10: =ROUND((BG10*BF10),2) -> 0 | BL10: =+$E$12 -> 1 | BM10: =$F$12 -> TRABAJOS PREPARATORIOS | BN10: =+$K$12*$BP$2 -> 452975.52 | BO10: =BN10/$BN$30 -> 0.0014978125
P11: SUBTOTAL MATERIALES - A - | T11: =SUM(T9:T10) -> 0 | X11: Alambre | Y11: Kg | Z11: 1 | AA11: 739.04185 | AB11: =+ROUND(Z11*AA11,2) -> 739.04 | AF11: Arena | AG11: M3 | AH11: 0.36 | AI11: 2066.1157 | AJ11: =+ROUND(AH11*AI11,2) -> 743.8 | AN11: SUBTOTAL MATERIALES - A - | AR11: =SUM(AR9:AR10) -> 33663.1 | AW11: Varios, carga, descarga y desperdicio | AX11: gl | AY11: 0.03 | AZ11: 13599128 | BA11: =+ROUND(AY11*AZ11,2) -> 407973.85 | BD11: Varios, carga, descarga y desperdicio | BE11: gl | BF11: 0.03 | BG11: 0 | BH11: =ROUND((BG11*BF11),2) -> 0 | BL11: =+$E$15 -> 2 | BM11: =$F$15 -> DEMOLICIONES | BN11: =+$K$15*$BP$2 -> 622029.59 | BO11: =BN11/$BN$30 -> 0.0020568081
E12: 1 | F12: TRABAJOS PREPARATORIOS | K12: =SUM(J13:J14) -> 285075.66 | L12: =+K12/$K$120 -> 0.0014978125 | P12: Mano de Obra: | X12: Clavos | Y12: Kg | Z12: 1 | AA12: 684.56365 | AB12: =+ROUND(Z12*AA12,2) -> 684.56 | AF12: Hierro | AG12: Kg | AH12: 1.05 | AI12: 27.236208 | AJ12: =+ROUND(AH12*AI12,2) -> 28.6 | AN12: Mano de Obra: | AW12: SUBTOTAL MATERIALES - A - | BA12: =SUM(BA9:BA11) -> 14007102 | BD12: SUBTOTAL MATERIALES - A - | BH12: =SUM(BH9:BH11) -> 0 | BL12: =+$E$23 -> 3 | BM12: =$F$23 -> MOVIMIENTO DE SUELO | BN12: =+$K$23*$BP$2 -> 113182.63 | BO12: =BN12/$BN$30 -> 0.0003742506
E13: 1.1 | F13: TRASLADO DE MUEBLES, CUADROS, PAPELERIA, ETC | G13: Gl | H13: 1 | I13: =+$T$23 -> 121923 | J13: =ROUND(I13*H13,2) -> 121923 | L13: =+J13/$K$120 -> 0.00064059412 | M13: =+L13 -> 0.00064059412 | P13: Oficial | Q13: hs | S13: 1600.8 | T13: =+ROUND(R13*S13,2) -> 0 | X13: Encofrado | Y13: m2 | Z13: 1.1 | AA13: 3370 | AB13: =+ROUND(Z13*AA13,2) -> 3707 | AF13: Varios, carga, descarga y desperdicio | AG13: gl | AH13: 0.03 | AI13: 14020.5 | AJ13: =+ROUND(AH13*AI13,2) -> 420.62 | AN13: Oficial | AO13: hs | AQ13: 1600.8 | AR13: =+ROUND(AP13*AQ13,2) -> 0 | AW13: Mano de Obra: | BD13: Mano de Obra: | BL13: =+$E$25 -> 4 | BM13: =$F$25 -> ESTRUCTURA RESISTENTE | BN13: =+$K$25*$BP$2 -> 21249056 | BO13: =BN13/$BN$30 -> 0.070262299
E14: 1.2 | F14: CARTEL DE OBRA | G14: m2 | H14: 8.64 | I14: =+$T$44 -> 18883.41 | J14: =ROUND(I14*H14,2) -> 163152.66 | L14: =+J14/$K$120 -> 0.00085721837 | M14: =+L14 -> 0.00085721837 | P14: Ayudante | Q14: hs | R14: 90 | S14: 1354.7 | T14: =+ROUND(R14*S14,2) -> 121923 | X14: Varios, carga, descarga y desperdicio | Y14: gl | Z14: 0.03 | AA14: 51972.68 | AB14: =+ROUND(Z14*AA14,2) -> 1559.18 | AF14: SUBTOTAL MATERIALES - A - | AJ14: =SUM(AJ9:AJ13) -> 14441.12 | AN14: Ayudante | AO14: hs | AQ14: 1354.7 | AR14: =+ROUND(AP14*AQ14,2) -> 0 | AW14: Oficial | AX14: hs | AY14: 40 | AZ14: 1600.8 | BA14: =+ROUND(AY14*AZ14,2) -> 64032 | BD14: Oficial | BE14: hs | BG14: 1600.8 | BH14: =+ROUND(BF14*BG14,2) -> 0 | BL14: =+$E$40 -> 5 | BM14: =$F$40 -> MAMPOSTERIA | BN14: =+$K$40*$BP$2 -> 2318511.6 | BO14: =BN14/$BN$30 -> 0.0076664091
E15: 2 | F15: DEMOLICIONES | K15: =SUM(J16:J22) -> 391468.17 | L15: =+K15/$K$120 -> 0.0020568081 | X15: SUBTOTAL MATERIALES - A - | AB15: =SUM(AB9:AB14) -> 83699.36 | AF15: Mano de Obra: | AW15: Ayudante | AX15: hs | AY15: 40 | AZ15: 1354.7 | BA15: =+ROUND(AY15*AZ15,2) -> 54188 | BD15: Ayudante | BE15: hs | BF15: 120 | BG15: 1354.7 | BH15: =+ROUND(BF15*BG15,2) -> 162564 | BL15: =+$E$45 -> 6 | BM15: =$F$45 -> AISLACION | BN15: =+$K$45*$BP$2 -> 2548672 | BO15: =BN15/$BN$30 -> 0.0084274593
E16: 2.1 | F16: DEMOLICION DE CIELORRASO EXISTENTE | G16: m2 | H16: 289.58 | I16: =+$T$62 -> 547.76 | J16: =ROUND(I16*H16,2) -> 158620.34 | L16: =+J16/$K$120 -> 0.00083340516 | M16: =+L16 -> 0.00083340516 | P16: SUBTOTAL MANO DE OBRA - B - | T16: =SUM(T13:T15) -> 121923 | X16: Mano de Obra: | AF16: Oficial | AG16: hs | AH16: 8 | AI16: 1600.8 | AJ16: =+ROUND(AH16*AI16,2) -> 12806.4 | AN16: SUBTOTAL MANO DE OBRA - B - | AR16: =SUM(AR13:AR15) -> 0 | BL16: =+$E$48 -> 7 | BM16: =$F$48 -> REVOQUE | BN16: =+$K$48*$BP$2 -> 2406120.7 | BO16: =BN16/$BN$30 -> 0.0079560982
E17: 2.2 | F17: RETIRO DE CARPINTERIAS EXISTENTES | G17: Un | H17: 2 | I17: =+$T$80 -> 3171.11 | J17: =ROUND(I17*H17,2) -> 6342.22 | L17: =+J17/$K$120 -> 3.3322579e-05 | M17: =+L17 -> 3.3322579e-05 | X17: Oficial | Y17: hs | Z17: 12 | AA17: 1600.8 | AB17: =+ROUND(Z17*AA17,2) -> 19209.6 | AF17: Ayudante | AG17: hs | AH17: 8 | AI17: 1354.7 | AJ17: =+ROUND(AH17*AI17,2) -> 10837.6 | AN17: Equipos: | AW17: SUBTOTAL MANO DE OBRA - B - | BA17: =SUM(BA14:BA16) -> 118220 | BB17: =+BA17/BA12 -> 0.0084400042 | BD17: SUBTOTAL MANO DE OBRA - B - | BH17: =SUM(BH14:BH16) -> 162564 | BL17: =+$E$52 -> 8 | BM17: =$F$52 -> REVESTIMIENTO | BN17: =+$K$52*$BP$2 -> 34097.032 | BO17: =BN17/$BN$30 -> 0.00011274552
E18: 2.3 | F18: RETIRO DE PAÑOS VIDRIADOS P/ OFICINAS | G18: m2 | H18: 23.04 | I18: =+T98 -> 1915.51 | J18: =ROUND(I18*H18,2) -> 44133.35 | L18: =+J18/$K$120 -> 0.00023188049 | M18: =+L18 -> 0.00023188049 | P18: Equipos: | X18: Ayudante | Y18: hs | Z18: 12 | AA18: 1354.7 | AB18: =+ROUND(Z18*AA18,2) -> 16256.4 | AN18: FLETE | AO18: KG | AP18: 60 | AQ18: 1.9600688 | AR18: =+ROUND(AP18*AQ18,2) -> 117.6 | AW18: Equipos: | BD18: Equipos: | BL18: =+$E$54 -> 9 | BM18: =$F$54 -> CUBIERTA DE CHº Gº | BN18: =+$K$54*$BP$2 -> 1304592.9 | BO18: =BN18/$BN$30 -> 0.0043137775
E19: 2.4 | F19: RETIRO DE BARANDAS EXISTENTES EN TERRAZA | G19: ml | H19: 18.77 | I19: =+$T$116 -> 470.22 | J19: =ROUND(I19*H19,2) -> 8826.03 | L19: =+J19/$K$120 -> 4.6372735e-05 | M19: =+L19 -> 4.6372735e-05 | P19: FLETE | Q19: KG | R19: 0 | S19: 1.9600688 | T19: =+ROUND(R19*S19,2) -> 0 | AF19: SUBTOTAL MANO DE OBRA - B - | AJ19: =SUM(AJ16:AJ18) -> 23644 | AN19: SUBTOTAL EQUIPOS - C - | AR19: =SUM(AR18:AR18) -> 117.6 | AW19: FLETE | AX19: KG | AY19: 360 | AZ19: 1.9600688 | BA19: =+ROUND(AY19*AZ19,2) -> 705.62 | BD19: FLETE | BE19: KG | BF19: 0 | BG19: 1.9600688 | BH19: =+ROUND(BF19*BG19,2) -> 0 | BL19: =+$E$58 -> 10 | BM19: =$F$58 -> TABIQUE DE PLACAS DE YESO | BN19: =+$K$58*$BP$2 -> 21201331 | BO19: =BN19/$BN$30 -> 0.07010449
E20: 2.5 | F20: DEMOLICION DE PISO Y CONTRAPISO P/ ASCENSOR | G20: m2 | H20: 5.681 | I20: =+$T$135 -> 860.5 | J20: =ROUND(I20*H20,2) -> 4888.5 | L20: =+J20/$K$120 -> 2.5684607e-05 | M20: =+L20 -> 2.5684607e-05 | P20: Equipos - Hormigonera | Q20: gl | S20: 686.94 | T20: =+ROUND(R20*S20,2) -> 0 | X20: SUBTOTAL MANO DE OBRA - B - | AB20: =SUM(AB17:AB19) -> 35466 | AF20: Equipos: | AN20: COSTO NETO TOTAL - D - | AP20: (A+B+C) | AR20: =+AR11+AR16+AR19 -> 33780.7 | AW20: SUBTOTAL EQUIPOS - C - | BA20: =SUM(BA19:BA19) -> 705.62 | BD20: CONTENEDOR | BE20: un | BF20: 60 | BG20: 5500 | BH20: =+ROUND(BF20*BG20,2) -> 330000 | BL20: =+$E$61 -> 11 | BM20: =$F$61 -> CIELORRASO | BN20: =+$K$61*$BP$2 -> 7141716 | BO20: =BN20/$BN$30 -> 0.023614856
E21: 2.6 | F21: DEMOLICION DE PISO DE TERRAZA | G21: m2 | H21: 87.4469 | I21: =+$T$154 -> 703.69 | J21: =ROUND(I21*H21,2) -> 61535.51 | L21: =+J21/$K$120 -> 0.00032331296 | M21: =+L21 -> 0.00032331296 | T21: =+ROUND(R21*S21,2) -> 0 | X21: Equipos: | AF21: FLETE | AG21: KG | AH21: 631.05 | AI21: 1.9600688 | AJ21: =+ROUND(AH21*AI21,2) -> 1236.9 | AW21: COSTO NETO TOTAL - D - | AY21: (A+B+C) | BA21: =+BA12+BA17+BA20 -> 14126028 | BD21: SUBTOTAL EQUIPOS - C - | BH21: =SUM(BH19:BH20) -> 330000 | BL21: =+$E$64 -> 12 | BM21: =$F$64 -> SOLADO Y ZOCALO | BN21: =+$K$64*$BP$2 -> 10821114 | BO21: =BN21/$BN$30 -> 0.035781181
E22: 2.7 | F22: RETIRO DE ESCOMBROS | G22: Gl | H22: 1 | I22: =+$T$173 -> 107122.22 | J22: =ROUND(I22*H22,2) -> 107122.22 | L22: =+J22/$K$120 -> 0.00056282953 | M22: =+L22 -> 0.00056282953 | P22: SUBTOTAL EQUIPOS - C - | T22: =SUM(T19:T21) -> 0 | X22: FLETE | Y22: KG | Z22: 141.25 | AA22: 1.9600688 | AB22: =+ROUND(Z22*AA22,2) -> 276.86 | AF22: SUBTOTAL EQUIPOS - C - | AJ22: =SUM(AJ21:AJ21) -> 1236.9 | AN22: 10 - TABIQUE DE PLACAS DE YESO | BD22: COSTO NETO TOTAL - D - | BF22: (A+B+C) | BH22: =+BH12+BH17+BH21 -> 492564 | BL22: =+$E$72 -> 13 | BM22: =$F$72 -> CARPINTERIA | BN22: =+$K$72*$BP$2 -> 22023711 | BO22: =BN22/$BN$30 -> 0.072823781
E23: 3 | F23: MOVIMIENTO DE SUELO | K23: =SUM(J24) -> 71230.37 | L23: =+K23/$K$120 -> 0.0003742506 | P23: COSTO NETO TOTAL - D - | R23: (A+B+C) | T23: =+T11+T16+T22 -> 121923 | X23: SUBTOTAL EQUIPOS - C - | AB23: =SUM(AB22:AB22) -> 276.86 | AF23: COSTO NETO TOTAL - D - | AH23: (A+B+C) | AJ23: =+AJ14+AJ19+AJ22 -> 39322.02 | AN23: 10.2 - TABIQUE DE PLACA DE YESO C/AISL | AR23: =$G$60 -> m2 | AS23: =$H$60 -> 153 | AW23: 16 - AIRE ACONDICIONADO | BL23: =+$E$90 -> 14 | BM23: =$F$90 -> INSTALACION ELECTRICA | BN23: =+$K$90*$BP$2 -> 1.3170524e+08 | BO23: =BN23/$BN$30 -> 0.4354976
E24: 3.1 | F24: EXCAVACION PARA FUNDACION PARA ASCENSOR | G24: m3 | H24: 8.5215 | I24: =+$T$191 -> 8358.9 | J24: =ROUND(I24*H24,2) -> 71230.37 | L24: =+J24/$K$120 -> 0.0003742506 | M24: =+L24 -> 0.0003742506 | X24: COSTO NETO TOTAL - D - | Z24: (A+B+C) | AB24: =+AB15+AB20+AB23 -> 119442.22 | AW24: 16.1 - RETIRO DE EQUIPOS | BA24: =$G$103 -> Gl | BB24: =$H$103 -> 1 | BD24: 18 - VARIOS | BL24: =+$E$100 -> 15 | BM24: =$F$100 -> INSTALACIÓN ELECTROMECÁNICA | BN24: =+$K$100*$BP$2 -> 22445777 | BO24: =BN24/$BN$30 -> 0.074219387
E25: 4 | F25: ESTRUCTURA RESISTENTE | K25: =SUM(J26:J39) -> 13372883 | L25: =+K25/$K$120 -> 0.070262299 | P25: 1 - TRABAJOS PREPARATORIOS | AF25: 5 - MAMPOSTERIA | AN25: DESCRIPCION | AO25: UNIDAD | AP25: CANTIDAD | AQ25: PRECIO | AR25: Subtotal | AS25: FLETE | BD25: 18.2 - CARTELES INDICADORES DE LOCAL | BH25: =$G$113 -> Un | BI25: =$H$113 -> 17 | BL25: =+$E$102 -> 16 | BM25: =$F$102 -> AIRE ACONDICIONADO | BN25: =+$K$102*$BP$2 -> 36155129 | BO25: =BN25/$BN$30 -> 0.11955084
E26: 4.1 | F26: ESTRUTURA DE HºAº | P26: 1.2 - CARTEL DE OBRA | T26: =$G$14 -> m2 | U26: =$H$14 -> 8.64 | X26: 4 - ESTRUCTURA RESISTENTE | AF26: 5.2 - MAMP. ARMADA LAD.COMUN - 0,18 | AJ26: =$G$42 -> m3 | AK26: =$H$42 -> 1.045 | AN26: Materiales: | AW26: DESCRIPCION | AX26: UNIDAD | AY26: CANTIDAD | AZ26: PRECIO | BA26: Subtotal | BB26: FLETE | BL26: =+$E$106 -> 17 | BM26: =$F$106 -> PINTURA | BN26: =+$K$106*$BP$2 -> 7335522.6 | BO26: =BN26/$BN$30 -> 0.024255698
E27: 4.1.1 | F27: HºAº PARA BASE ASCENSOR - H30 | G27: m3 | H27: 1.878225 | I27: =+$AB$24 -> 119442.22 | J27: =ROUND(I27*H27,2) -> 224339.36 | L27: =+J27/$K$120 -> 0.0011786986 | M27: =+L27 -> 0.0011786986 | X27: 4.2.1 - ESTRCTURA METALICA ASCENSOR | AB27: =$G$29 -> Gl | AC27: =$H$29 -> 1 | AN27: TABIQUE DE PLACA DE YESO C/AISL | AO27: gl | AP27: 1.05 | AQ27: 7334.985 | AR27: =+ROUND(AP27*AQ27,2) -> 7701.73 | AW27: Materiales: | BD27: DESCRIPCION | BE27: UNIDAD | BF27: CANTIDAD | BG27: PRECIO | BH27: Subtotal | BI27: FLETE | BL27: =+$E$111 -> 18 | BM27: =$F$111 -> VARIOS | BN27: =+$K$111*$BP$2 -> 12545939 | BO27: =BN27/$BN$30 -> 0.041484504
E28: 4.2 | F28: ESTRUTURA METALICA | P28: DESCRIPCION | Q28: UNIDAD | R28: CANTIDAD | S28: PRECIO | T28: Subtotal | U28: FLETE | AF28: DESCRIPCION | AG28: UNIDAD | AH28: CANTIDAD | AI28: PRECIO | AJ28: Subtotal | AK28: FLETE | AN28: Varios, carga, descarga y desperdicio | AO28: gl | AP28: 0.03 | AQ28: 7701.73 | AR28: =+ROUND(AP28*AQ28,2) -> 231.05 | BA28: =+ROUND(AY28*AZ28,2) -> 0 | BD28: Materiales:
E29: 4.2.1 | F29: ESTRCTURA METALICA ASCENSOR | G29: Gl | H29: 1 | I29: =+$AB$43 -> 5849381 | J29: =ROUND(I29*H29,2) -> 5849381 | L29: =+J29/$K$120 -> 0.03073316 | M29: =+L29 -> 0.03073316 | P29: Materiales: | X29: DESCRIPCION | Y29: UNIDAD | Z29: CANTIDAD | AA29: PRECIO | AB29: Subtotal | AC29: FLETE | AF29: Materiales: | AN29: SUBTOTAL MATERIALES - A - | AR29: =SUM(AR27:AR28) -> 7932.78 | BA29: =+ROUND(AY29*AZ29,2) -> 0 | BD29: 18.2 - CARTELES INDICADORES DE LOCAL | BE29: UN | BF29: 1 | BG29: 1177 | BH29: =ROUND((BG29*BF29),2) -> 1177
E30: 4.2.3 | F30: COLUMNAS METALICAS -Co- ESTUDIO-CON REFUERZO DE APOYOS SOBRE LOSAS PRETENSADAS | G30: ml | H30: 98.13 | I30: =+$AB$62 -> 18257.18 | J30: =ROUND(I30*H30,2) -> 1791577.1 | L30: =+J30/$K$120 -> 0.0094131029 | M30: =+L30 -> 0.0094131029 | P30: Cartel de Obra | Q30: m2 | R30: 1 | S30: 16497.585 | T30: =+ROUND(R30*S30,2) -> 16497.58 | X30: Materiales: | AF30: Ladrillos Comunes | AG30: Un | AH30: 290 | AI30: 37.45 | AJ30: =+ROUND(AH30*AI30,2) -> 10860.5 | AN30: Mano de Obra: | AS30: =+AR27*AS23 -> 1178364.7 | AW30: Varios, carga, descarga y desperdicio | AX30: gl | AY30: 0.03 | AZ30: 0 | BA30: =+ROUND(AY30*AZ30,2) -> 0 | BD30: Varios, carga, descarga y desperdicio | BE30: gl | BF30: 0.03 | BG30: 1177 | BH30: =ROUND((BG30*BF30),2) -> 35.31 | BN30: =SUM(BN10:BN29) -> 3.0242472e+08 | BO30: =SUM(BO10:BO29) -> 1
E31: 4.2.4 | F31: VIGAS METALICAS - VM1-ESTUDIO | G31: ml | H31: 43.67 | I31: =+$AB$81 -> 7920.91 | J31: =ROUND(I31*H31,2) -> 345906.14 | L31: =+J31/$K$120 -> 0.0018174212 | M31: =+L31 -> 0.0018174212 | P31: Varios, carga, descarga y desperdicio | Q31: gl | R31: 0.03 | S31: 16497.58 | T31: =+ROUND(R31*S31,2) -> 494.93 | X31: 4.2.1 - ESTRCTURA METALICA ASCENSOR | Y31: GL | Z31: 1 | AA31: 4441229 | AB31: =+ROUND(Z31*AA31,2) -> 4441229 | AF31: Cemento | AG31: Kg | AH31: 90 | AI31: 26.528938 | AJ31: =+ROUND(AH31*AI31,2) -> 2387.6 | AN31: Oficial | AO31: hs | AQ31: 1600.8 | AR31: =+ROUND(AP31*AQ31,2) -> 0 | AW31: SUBTOTAL MATERIALES - A - | BA31: =SUM(BA28:BA30) -> 0 | BD31: SUBTOTAL MATERIALES - A - | BH31: =SUM(BH29:BH30) -> 1212.31
E32: 4.2.5 | F32: VIGAS METALICAS - VM2-ESTUDIO | G32: ml | H32: 19.36 | I32: =+$AB$100 -> 14954.19 | J32: =ROUND(I32*H32,2) -> 289513.12 | L32: =+J32/$K$120 -> 0.0015211273 | M32: =+L32 -> 0.0015211273 | P32: SUBTOTAL MATERIALES - A - | T32: =SUM(T30:T31) -> 16992.51 | X32: ANCLANJES | Y32: GL | Z32: 1 | AA32: 62300 | AB32: =+ROUND(Z32*AA32,2) -> 62300 | AF32: Arena | AG32: M3 | AH32: 0.36 | AI32: 2066.1157 | AJ32: =+ROUND(AH32*AI32,2) -> 743.8 | AN32: Ayudante | AO32: hs | AQ32: 1354.7 | AR32: =+ROUND(AP32*AQ32,2) -> 0 | AW32: Mano de Obra: | BD32: Mano de Obra:
E33: 4.2.6 | F33: VIGAS METALICAS - VM3-AG.FOCO | G33: ml | H33: 13.64 | I33: =+$AB$119 -> 6605.05 | J33: =ROUND(I33*H33,2) -> 90092.88 | L33: =+J33/$K$120 -> 0.00047335588 | M33: =+L33 -> 0.00047335588 | P33: Mano de Obra: | X33: Varios, carga, descarga y desperdicio | Y33: gl | Z33: 0.03 | AA33: 1351058.7 | AB33: =+ROUND(Z33*AA33,2) -> 40531.76 | AF33: Hierro | AG33: Kg | AH33: 1.785 | AI33: 27.236208 | AJ33: =+ROUND(AH33*AI33,2) -> 48.62 | AW33: Oficial | AX33: hs | AY33: 40 | AZ33: 1600.8 | BA33: =+ROUND(AY33*AZ33,2) -> 64032 | BD33: Oficial | BE33: hs | BF33: 0.3 | BG33: 1600.8 | BH33: =+ROUND(BF33*BG33,2) -> 480.24 | BN33: =+$K$128 -> 3.0242472e+08 | BO33: =BO30-1 -> 0
E34: 4.2.7 | F34: VIGAS METALICAS - VM4-AG.FOCO | G34: ml | H34: 22.22 | I34: =+$AB$138 -> 12322.48 | J34: =ROUND(I34*H34,2) -> 273805.51 | L34: =+J34/$K$120 -> 0.0014385981 | M34: =+L34 -> 0.0014385981 | P34: Oficial | Q34: hs | R34: 0.6 | S34: 1600.8 | T34: =+ROUND(R34*S34,2) -> 960.48 | X34: SUBTOTAL MATERIALES - A - | AB34: =SUM(AB31:AB33) -> 4544060.8 | AF34: Varios, carga, descarga y desperdicio | AG34: gl | AH34: 0.03 | AI34: 14040.52 | AJ34: =+ROUND(AH34*AI34,2) -> 421.22 | AN34: SUBTOTAL MANO DE OBRA - B - | AR34: =SUM(AR31:AR33) -> 0 | AW34: Ayudante | AX34: hs | AY34: 40 | AZ34: 1354.7 | BA34: =+ROUND(AY34*AZ34,2) -> 54188 | BD34: Ayudante | BE34: hs | BG34: 1354.7 | BH34: =+ROUND(BF34*BG34,2) -> 0 | BN34: =+BN33-BN30 -> 0
E35: 4.2.8 | F35: VIGAS METALICAS - VM6-AG.FOCO | G35: ml | H35: 13.2 | I35: =+$AB$176 -> 11701.2 | J35: =ROUND(I35*H35,2) -> 154455.84 | L35: =+J35/$K$120 -> 0.00081152451 | M35: =+L35 -> 0.00081152451 | P35: Ayudante | Q35: hs | R35: 0.6 | S35: 1354.7 | T35: =+ROUND(R35*S35,2) -> 812.82 | X35: Mano de Obra: | AF35: SUBTOTAL MATERIALES - A - | AJ35: =SUM(AJ30:AJ34) -> 14461.74 | AN35: Equipos:
E36: 4.2.9 | F36: VIGAS METALICAS - VM7-ESTUDIO | G36: ml | H36: 26.4 | I36: =+$AB$157 -> 12322.48 | J36: =ROUND(I36*H36,2) -> 325313.47 | L36: =+J36/$K$120 -> 0.0017092255 | M36: =+L36 -> 0.0017092255 | X36: Oficial | Y36: hs | Z36: 440 | AA36: 1600.8 | AB36: =+ROUND(Z36*AA36,2) -> 704352 | AF36: Mano de Obra: | AN36: FLETE | AO36: KG | AP36: 40 | AQ36: 1.9600688 | AR36: =+ROUND(AP36*AQ36,2) -> 78.4 | AW36: SUBTOTAL MANO DE OBRA - B - | BA36: =SUM(BA33:BA35) -> 118220 | BD36: SUBTOTAL MANO DE OBRA - B - | BH36: =SUM(BH33:BH35) -> 480.24
E37: 4.2.10 | F37: VIGAS METALICAS - VM5-ESTUDIO - REFUERZO SUPERIOR | G37: ml | H37: 15.98 | I37: =+$AB$195 -> 148090.25 | J37: =ROUND(I37*H37,2) -> 2366482.2 | L37: =+J37/$K$120 -> 0.012433705 | M37: =+L37 -> 0.012433705 | P37: SUBTOTAL MANO DE OBRA - B - | T37: =SUM(T34:T36) -> 1773.3 | X37: Ayudante | Y37: hs | Z37: 440 | AA37: 1354.7 | AB37: =+ROUND(Z37*AA37,2) -> 596068 | AF37: Oficial | AG37: hs | AH37: 8 | AI37: 1600.8 | AJ37: =+ROUND(AH37*AI37,2) -> 12806.4 | AN37: SUBTOTAL EQUIPOS - C - | AR37: =SUM(AR36:AR36) -> 78.4 | AW37: Equipos: | BD37: Equipos:
E38: 4.2.11 | F38: CORREAS METALICAS - ENTREPISO - ESTUDIO-AG.FOCO | G38: ml | H38: 280.5 | I38: =+$AB$214 -> 4119 | J38: =ROUND(I38*H38,2) -> 1155379.5 | L38: =+J38/$K$120 -> 0.0060704651 | M38: =+L38 -> 0.0060704651 | AF38: Ayudante | AG38: hs | AH38: 8 | AI38: 1354.7 | AJ38: =+ROUND(AH38*AI38,2) -> 10837.6 | AN38: COSTO NETO TOTAL - D - | AP38: (A+B+C) | AR38: =+AR29+AR34+AR37 -> 8011.18 | AW38: FLETE | AX38: KG | AY38: 360 | AZ38: 1.9600688 | BA38: =+ROUND(AY38*AZ38,2) -> 705.62 | BD38: FLETE | BE38: KG | BF38: 0 | BG38: 1.9600688 | BH38: =+ROUND(BF38*BG38,2) -> 0
E39: 4.2.12 | F39: CORREAS PARA CUBIERTA NUEVA-AG.FOCO | G39: ml | H39: 123 | I39: =+$AB$214 -> 4119 | J39: =ROUND(I39*H39,2) -> 506637 | L39: =+J39/$K$120 -> 0.0026619152 | M39: =+L39 -> 0.0026619152 | P39: Equipos: | X39: SUBTOTAL MANO DE OBRA - B - | AB39: =SUM(AB36:AB38) -> 1300420 | AW39: SUBTOTAL EQUIPOS - C - | BA39: =SUM(BA38:BA38) -> 705.62 | BH39: =+ROUND(BF39*BG39,2) -> 0
E40: 5 | F40: MAMPOSTERIA | K40: =SUM(J41:J44) -> 1459132.3 | L40: =+K40/$K$120 -> 0.0076664091 | P40: FLETE | Q40: KG | R40: 60 | S40: 1.9600688 | T40: =+ROUND(R40*S40,2) -> 117.6 | X40: Equipos: | AF40: SUBTOTAL MANO DE OBRA - B - | AJ40: =SUM(AJ37:AJ39) -> 23644 | AN40: 11 - CIELORRASO | AW40: COSTO NETO TOTAL - D - | AY40: (A+B+C) | BA40: =+BA31+BA36+BA39 -> 118925.62 | BD40: SUBTOTAL EQUIPOS - C - | BH40: =SUM(BH38:BH39) -> 0
E41: 5.1 | F41: MAMP. ELEVACION LAD.COMUN - 0,18 | G41: m3 | H41: 35.11 | I41: =+$AJ$23 -> 39322.02 | J41: =ROUND(I41*H41,2) -> 1380596.1 | L41: =+J41/$K$120 -> 0.007253773 | M41: =+L41 -> 0.007253773 | P41: Equipos - Hormigonera | Q41: gl | S41: 686.94 | T41: =+ROUND(R41*S41,2) -> 0 | X41: FLETE | Y41: KG | Z41: 2500 | AA41: 1.9600688 | AB41: =+ROUND(Z41*AA41,2) -> 4900.17 | AF41: Equipos: | AN41: 11.1 - CIELORRASO DESMONTABLE PLACA EXSOUND C/LV 70mm | AR41: =$G$62 -> m2 | AS41: =$H$62 -> 145.5 | BD41: COSTO NETO TOTAL - D - | BF41: (A+B+C) | BH41: =+BH31+BH36+BH40 -> 1692.55
E42: 5.2 | F42: MAMP. ARMADA LAD.COMUN - 0,18 | G42: m3 | H42: 1.045 | I42: =+$AJ$23 -> 39322.02 | J42: =ROUND(I42*H42,2) -> 41091.51 | L42: =+J42/$K$120 -> 0.00021589839 | M42: =+L42 -> 0.00021589839 | T42: =+ROUND(R42*S42,2) -> 0 | X42: SUBTOTAL EQUIPOS - C - | AB42: =SUM(AB41:AB41) -> 4900.17 | AF42: FLETE | AG42: KG | AH42: 631.785 | AI42: 1.9600688 | AJ42: =+ROUND(AH42*AI42,2) -> 1238.34 | AW42: 16 - AIRE ACONDICIONADO
E43: 5.3 | F43: REFUERZOS (2 Fe 6mm, concreto) | G43: ml | H43: 52.8 | I43: =+$AJ$64 -> 354.59 | J43: =ROUND(I43*H43,2) -> 18722.35 | L43: =+J43/$K$120 -> 9.8368867e-05 | M43: =+L43 -> 9.8368867e-05 | P43: SUBTOTAL EQUIPOS - C - | T43: =SUM(T40:T42) -> 117.6 | X43: COSTO NETO TOTAL - D - | Z43: (A+B+C) | AB43: =+AB34+AB39+AB42 -> 5849381 | AF43: SUBTOTAL EQUIPOS - C - | AJ43: =SUM(AJ42:AJ42) -> 1238.34 | AN43: DESCRIPCION | AO43: UNIDAD | AP43: CANTIDAD | AQ43: PRECIO | AR43: Subtotal | AS43: FLETE | AW43: 16.2 - PROVISIÓN E INSTALACIÓN EQUIPO VRF - FRÍO/CALOR - ESTUDIO | BA43: =$G$104 -> Gl | BB43: =$H$104 -> 1 | BD43: 18 - VARIOS
E44: 5.4 | F44: DINTEL (2 Fe 8mm, concreto) | G44: ml | H44: 52.8 | I44: =+$AJ$84 -> 354.59 | J44: =ROUND(I44*H44,2) -> 18722.35 | L44: =+J44/$K$120 -> 9.8368867e-05 | M44: =+L44 -> 9.8368867e-05 | P44: COSTO NETO TOTAL - D - | R44: (A+B+C) | T44: =+T32+T37+T43 -> 18883.41 | AF44: COSTO NETO TOTAL - D - | AH44: (A+B+C) | AJ44: =+AJ35+AJ40+AJ43 -> 39344.08 | AN44: Materiales: | BD44: 18.3 - PASARELAS METALICAS ESTUDIO | BH44: =$G$114 -> UN | BI44: =$H$114 -> 1
E45: 6 | F45: AISLACION | K45: =SUM(J46:J47) -> 1603981.5 | L45: =+K45/$K$120 -> 0.0084274593 | X45: 4 - ESTRUCTURA RESISTENTE | AN45: CIELORRASO DESMONTABLE PLACA EXSOUND C/LV 70mm | AO45: M2 | AP45: 1.03 | AQ45: 17812.691 | AR45: =+ROUND(AP45*AQ45,2) -> 18347.07 | AW45: DESCRIPCION | AX45: UNIDAD | AY45: CANTIDAD | AZ45: PRECIO | BA45: Subtotal | BB45: FLETE
E46: 6.1 | F46: ESPUMA DE POLIURETANO INYECTADO BAJO CHAPA ESTUDIO | G46: m2 | H46: 315 | I46: =+$AJ$102 -> 4123.78 | J46: =ROUND(I46*H46,2) -> 1298990.7 | L46: =+J46/$K$120 -> 0.0068250109 | M46: =+L46 -> 0.0068250109 | P46: 2 - DEMOLICIONES | X46: 4.2.3 - COLUMNAS METALICAS -Co- ESTUDIO-CON REFUERZO DE APOYOS SOBRE LOSAS PRETENSADAS | AB46: =$G$30 -> ml | AC46: =$H$30 -> 98.13 | AF46: 5 - MAMPOSTERIA | AN46: Varios, carga, descarga y desperdicio | AO46: gl | AP46: 0.03 | AQ46: 18347.07 | AR46: =+ROUND(AP46*AQ46,2) -> 550.41 | AW46: Materiales: | BD46: DESCRIPCION | BE46: UNIDAD | BF46: CANTIDAD | BG46: PRECIO | BH46: Subtotal | BI46: FLETE
E47: 6.2 | F47: ESPUMA DE POLIETILENO ALUMINIZADA TBA 10mm | G47: m2 | H47: 120 | I47: =+$AJ$121 -> 2541.59 | J47: =ROUND(I47*H47,2) -> 304990.8 | L47: =+J47/$K$120 -> 0.0016024484 | M47: =+L47 -> 0.0016024484 | P47: 2.1 - DEMOLICION DE CIELORRASO EXISTENTE | T47: =$G$16 -> m2 | U47: =$H$16 -> 289.58 | AF47: 5.3 - REFUERZOS (2 Fe 6mm, concreto) | AJ47: =$G$43 -> ml | AK47: =$H$43 -> 52.8 | AN47: SUBTOTAL MATERIALES - A - | AR47: =SUM(AR45:AR46) -> 18897.48 | AW47: PROVISIÓN E INSTALACIÓN EQUIPO VRF - FRÍO/CALOR - ESTUDIO | AX47: un | AY47: 1 | AZ47: 20891285 | BA47: =+ROUND(AY47*AZ47,2) -> 20891285 | BD47: Materiales:
E48: 7 | F48: REVOQUE | K48: =SUM(J49:J51) -> 1514268.3 | L48: =+K48/$K$120 -> 0.0079560982 | X48: DESCRIPCION | Y48: UNIDAD | Z48: CANTIDAD | AA48: PRECIO | AB48: Subtotal | AC48: FLETE | AN48: Mano de Obra: | AS48: =+AR45*AS41 -> 2669498.7 | AW48: Varios de conexionado | AX48: gl | AY48: 1 | AZ48: 146238.99 | BA48: =+ROUND(AY48*AZ48,2) -> 146239 | BD48: 18.3 - PASARELAS METALICAS ESTUDIO | BE48: UN | BF48: 1 | BG48: 3712826.6 | BH48: =ROUND((BG48*BF48),2) -> 3712826.6 | BJ48: =+BH48*BI44 -> 3712826.6
E49: 7.1 | F49: REVOQUE EXTERIOR 3:1 | G49: m2 | H49: 232.288 | I49: =+$AJ$140 -> 3730.89 | J49: =ROUND(I49*H49,2) -> 866640.98 | L49: =+J49/$K$120 -> 0.0045534076 | M49: =+L49 -> 0.0045534076 | P49: DESCRIPCION | Q49: UNIDAD | R49: CANTIDAD | S49: PRECIO | T49: Subtotal | U49: FLETE | X49: Materiales: | AF49: DESCRIPCION | AG49: UNIDAD | AH49: CANTIDAD | AI49: PRECIO | AJ49: Subtotal | AK49: FLETE | AN49: Oficial | AO49: hs | AQ49: 1600.8 | AR49: =+ROUND(AP49*AQ49,2) -> 0 | AW49: Varios, carga, descarga y desperdicio | AX49: gl | AY49: 0.03 | AZ49: 21037524 | BA49: =+ROUND(AY49*AZ49,2) -> 631125.72 | BD49: sujeciones,fijaciones,etc | BE49: gl | BF49: 1 | BG49: 85395.012 | BH49: =ROUND((BG49*BF49),2) -> 85395.01
E50: 7.2 | F50: REVOQUE INTERIOR 2:1 | G50: m2 | H50: 190.4 | I50: =+$AJ$159 -> 3369.66 | J50: =ROUND(I50*H50,2) -> 641583.26 | L50: =+J50/$K$120 -> 0.0033709347 | M50: =+L50 -> 0.0033709347 | P50: Materiales: | X50: 4.2.3 - COLUMNAS METALICAS -Co- ESTUDIO-CON REFUERZO DE APOYOS SOBRE LOSAS PRETENSADAS | Y50: m | Z50: 1.1 | AA50: 14344.29 | AB50: =+ROUND(Z50*AA50,2) -> 15778.72 | AF50: Materiales: | AN50: Ayudante | AO50: hs | AQ50: 1354.7 | AR50: =+ROUND(AP50*AQ50,2) -> 0 | AW50: SUBTOTAL MATERIALES - A - | BA50: =SUM(BA47:BA49) -> 21668650 | BD50: Varios, carga, descarga y desperdicio | BE50: gl | BF50: 0.03 | BG50: 1139466.5 | BH50: =ROUND((BG50*BF50),2) -> 34183.99
E51: 7.3 | F51: REVOQUE BAJO REVESTIMIENTO 3:1 | G51: m2 | H51: 1.62 | I51: =+$AJ$140 -> 3730.89 | J51: =ROUND(I51*H51,2) -> 6044.04 | L51: =+J51/$K$120 -> 3.1755916e-05 | M51: =+L51 -> 3.1755916e-05 | T51: =+ROUND(R51*S51,2) -> 0 | X51: Sujeciones,fijaciones p/apoyos | Y51: gl | Z51: 1 | AA51: 473.3616 | AB51: =+ROUND(Z51*AA51,2) -> 473.36 | AF51: Cemento | AG51: Kg | AH51: 0.5 | AI51: 26.528938 | AJ51: =+ROUND(AH51*AI51,2) -> 13.26 | AW51: Mano de Obra: | BD51: SUBTOTAL MATERIALES - A - | BH51: =SUM(BH48:BH50) -> 3832405.6
E52: 8 | F52: REVESTIMIENTO | K52: =SUM(J53:J53) -> 21458.63 | L52: =+K52/$K$120 -> 0.00011274552 | P52: Varios, carga, descarga y desperdicio | Q52: gl | R52: 0.03 | T52: =+ROUND(R52*S52,2) -> 0 | X52: Varios, carga, descarga y desperdicio | Y52: gl | Z52: 0.03 | AA52: 16252.08 | AB52: =+ROUND(Z52*AA52,2) -> 487.56 | AF52: Arena | AG52: m3 | AH52: 0.006 | AI52: 2066.1157 | AJ52: =+ROUND(AH52*AI52,2) -> 12.4 | AN52: SUBTOTAL MANO DE OBRA - B - | AR52: =SUM(AR49:AR51) -> 0 | AW52: Oficial | AX52: hs | AY52: 80 | AZ52: 1600.8 | BA52: =+ROUND(AY52*AZ52,2) -> 128064 | BD52: Mano de Obra:
E53: 8.1 | F53: PORCELANATO - OFFICE | G53: m2 | H53: 1.62 | I53: =+$AJ$180 -> 13246.07 | J53: =ROUND(I53*H53,2) -> 21458.63 | L53: =+J53/$K$120 -> 0.00011274552 | M53: =+L53 -> 0.00011274552 | P53: SUBTOTAL MATERIALES - A - | T53: =SUM(T51:T52) -> 0 | X53: SUBTOTAL MATERIALES - A - | AB53: =SUM(AB50:AB52) -> 16739.64 | AF53: Hierro | AG53: Kg | AH53: 0.4662 | AI53: 27.236208 | AJ53: =+ROUND(AH53*AI53,2) -> 12.7 | AN53: Equipos: | AW53: Ayudante | AX53: hs | AY53: 40 | AZ53: 1354.7 | BA53: =+ROUND(AY53*AZ53,2) -> 54188 | BD53: Oficial | BE53: hs | BF53: 440 | BG53: 1600.8 | BH53: =+ROUND(BF53*BG53,2) -> 704352
E54: 9 | F54: CUBIERTA DE CHº Gº | K54: =SUM(J55:J57) -> 821032.65 | L54: =+K54/$K$120 -> 0.0043137775 | P54: Mano de Obra: | X54: Mano de Obra: | AF54: Varios, carga, descarga y desperdicio | AG54: gl | AH54: 0.03 | AI54: 38.36 | AJ54: =+ROUND(AH54*AI54,2) -> 1.15 | AN54: FLETE | AO54: KG | AP54: 60 | AQ54: 1.9600688 | AR54: =+ROUND(AP54*AQ54,2) -> 117.6 | BD54: Ayudante | BE54: hs | BF54: 440 | BG54: 1354.7 | BH54: =+ROUND(BF54*BG54,2) -> 596068
E55: 9.1 | F55: CHAPA GALVANIZADA Nº 25 | G55: m2 | H55: 92.6 | I55: =+$AJ$200 -> 6661.01 | J55: =ROUND(I55*H55,2) -> 616809.53 | L55: =+J55/$K$120 -> 0.0032407713 | M55: =+L55 -> 0.0032407713 | P55: Oficial | Q55: hs | R55: 0.1 | S55: 1600.8 | T55: =+ROUND(R55*S55,2) -> 160.08 | X55: Oficial | Y55: hs | Z55: 0.5 | AA55: 1600.8 | AB55: =+ROUND(Z55*AA55,2) -> 800.4 | AF55: SUBTOTAL MATERIALES - A - | AJ55: =SUM(AJ51:AJ54) -> 39.51 | AN55: SUBTOTAL EQUIPOS - C - | AR55: =SUM(AR54:AR54) -> 117.6 | AW55: SUBTOTAL MANO DE OBRA - B - | BA55: =SUM(BA52:BA54) -> 182252 | BB55: =+BA55/BA50 -> 0.008410861
E56: 9.2 | F56: CANALETAS CHº Gº | G56: ml | H56: 12.35 | I56: =+$AJ$220 -> 5832.9 | J56: =ROUND(I56*H56,2) -> 72036.32 | L56: =+J56/$K$120 -> 0.00037848514 | M56: =+L56 -> 0.00037848514 | P56: Ayudante | Q56: hs | R56: 0.25 | S56: 1354.7 | T56: =+ROUND(R56*S56,2) -> 338.68 | X56: Ayudante | Y56: hs | Z56: 0.5 | AA56: 1354.7 | AB56: =+ROUND(Z56*AA56,2) -> 677.35 | AF56: Mano de Obra: | AK56: =+AJ51*AK47 -> 700.128 | AN56: COSTO NETO TOTAL - D - | AP56: (A+B+C) | AR56: =+AR47+AR52+AR55 -> 19015.08 | AW56: Equipos: | BD56: SUBTOTAL MANO DE OBRA - B - | BH56: =SUM(BH53:BH55) -> 1300420 | BI56: =+BH56/BH51 -> 0.33932212
E57: 9.3 | F57: ZINGUERIA P/ ENCUENTROS CHº Gº | G57: ml | H57: 32.2 | I57: =+$AJ$240 -> 4105.18 | J57: =ROUND(I57*H57,2) -> 132186.8 | L57: =+J57/$K$120 -> 0.00069452103 | M57: =+L57 -> 0.00069452103 | AF57: Oficial | AG57: hs | AH57: 0.1 | AI57: 1600.8 | AJ57: =+ROUND(AH57*AI57,2) -> 160.08 | AW57: FLETE | AX57: KG | AY57: 2400 | AZ57: 1.9600688 | BA57: =+ROUND(AY57*AZ57,2) -> 4704.17 | BD57: Equipos:
E58: 10 | F58: TABIQUE DE PLACAS DE YESO | K58: =SUM(J59:J60) -> 13342848 | L58: =+K58/$K$120 -> 0.07010449 | P58: SUBTOTAL MANO DE OBRA - B - | T58: =SUM(T55:T57) -> 498.76 | X58: SUBTOTAL MANO DE OBRA - B - | AB58: =SUM(AB55:AB57) -> 1477.75 | AC58: =+AB58/AB53 -> 0.088278481 | AF58: Ayudante | AG58: hs | AH58: 0.1 | AI58: 1354.7 | AJ58: =+ROUND(AH58*AI58,2) -> 135.47 | AN58: 11 - CIELORRASO | AW58: SUBTOTAL EQUIPOS - C - | BA58: =SUM(BA57:BA57) -> 4704.17 | BD58: FLETE | BE58: KG | BF58: 1500 | BG58: 1.9600688 | BH58: =+ROUND(BF58*BG58,2) -> 2940.1
E59: 10.1 | F59: TABIQUE DE PLACA DE YESO - DOBLE PLACA, LANA DE VIDRIO 70mm-ESTUDIO | G59: m2 | H59: 358.7 | I59: =+$AR$20 -> 33780.7 | J59: =ROUND(I59*H59,2) -> 12117137 | L59: =+J59/$K$120 -> 0.0636645 | M59: =+L59 -> 0.0636645 | P59: Equipos: | X59: Equipos: | AN59: 11.2 - CIELORRASO DE PLACA DE YESO - JUNTA TOMADA LANA DE VIDRIO 50mm | AR59: =$G$63 -> m2 | AS59: =$H$63 -> 175.4 | AW59: COSTO NETO TOTAL - D - | AY59: (A+B+C) | BA59: =+BA50+BA55+BA58 -> 21855606 | BD59: SUBTOTAL EQUIPOS - C - | BH59: =SUM(BH58:BH58) -> 2940.1
E60: 10.2 | F60: TABIQUE DE PLACA DE YESO C/AISL | G60: m2 | H60: 153 | I60: =+$AR$38 -> 8011.18 | J60: =ROUND(I60*H60,2) -> 1225710.5 | L60: =+J60/$K$120 -> 0.0064399906 | M60: =+L60 -> 0.0064399906 | P60: FLETE | Q60: KG | R60: 25 | S60: 1.9600688 | T60: =+ROUND(R60*S60,2) -> 49 | X60: FLETE | Y60: KG | Z60: 20.3 | AA60: 1.9600688 | AB60: =+ROUND(Z60*AA60,2) -> 39.79 | AF60: SUBTOTAL MANO DE OBRA - B - | AJ60: =SUM(AJ57:AJ59) -> 295.55 | BD60: COSTO NETO TOTAL - D - | BF60: (A+B+C) | BH60: =+BH51+BH56+BH59 -> 5135765.7
E61: 11 | F61: CIELORRASO | K61: =SUM(J62:J63) -> 4494568.3 | L61: =+K61/$K$120 -> 0.023614856 | P61: SUBTOTAL EQUIPOS - C - | T61: =SUM(T60:T60) -> 49 | X61: SUBTOTAL EQUIPOS - C - | AB61: =SUM(AB60:AB60) -> 39.79 | AF61: Equipos: | AN61: DESCRIPCION | AO61: UNIDAD | AP61: CANTIDAD | AQ61: PRECIO | AR61: Subtotal | AS61: FLETE | AW61: 16 - AIRE ACONDICIONADO
E62: 11.1 | F62: CIELORRASO DESMONTABLE PLACA EXSOUND C/LV 70mm | G62: m2 | H62: 145.5 | I62: =+$AR$56 -> 19015.08 | J62: =ROUND(I62*H62,2) -> 2766694.1 | L62: =+J62/$K$120 -> 0.014536453 | M62: =+L62 -> 0.014536453 | P62: COSTO NETO TOTAL - D - | R62: (A+B+C) | T62: =+T53+T58+T61 -> 547.76 | X62: COSTO NETO TOTAL - D - | Z62: (A+B+C) | AB62: =+AB53+AB58+AB61 -> 18257.18 | AF62: FLETE | AG62: KG | AH62: 9.9662 | AI62: 1.9600688 | AJ62: =+ROUND(AH62*AI62,2) -> 19.53 | AN62: Materiales: | AW62: 16.3 - PROVISIÓN E INSTALACIÓN SPLIT 4500 FRIGORÍAS - FRÍO/CALOR-SALA TOM | BA62: =$G$105 -> UN | BB62: =$H$105 -> 2 | BD62: 18 - VARIOS
E63: 11.2 | F63: CIELORRASO DE PLACA DE YESO - JUNTA TOMADA LANA DE VIDRIO 50mm | G63: m2 | H63: 175.4 | I63: =+$AR$74 -> 9851.05 | J63: =ROUND(I63*H63,2) -> 1727874.2 | L63: =+J63/$K$120 -> 0.0090784023 | M63: =+L63 -> 0.0090784023 | AF63: SUBTOTAL EQUIPOS - C - | AJ63: =SUM(AJ62:AJ62) -> 19.53 | AN63: CIELORRASO DE PLACA DE YESO - JUNTA TOMADA LANA DE VIDRIO 50mm | AO63: ml | AP63: 1.03 | AQ63: 6425.8137 | AR63: =+ROUND(AP63*AQ63,2) -> 6618.59 | BD63: 18.4 - ESCALERA METALICA - RECTA, UN TRAMO C/BARANDA - ESTUDIO | BH63: =$G$115 -> UN | BI63: =$H$115 -> 1
E64: 12 | F64: SOLADO Y ZOCALO | K64: =SUM(J65:J71) -> 6810160.8 | L64: =+K64/$K$120 -> 0.035781181 | P64: 2 - DEMOLICIONES | X64: 4 - ESTRUCTURA RESISTENTE | AF64: COSTO NETO TOTAL - D - | AH64: (A+B+C) | AJ64: =+AJ55+AJ60+AJ63 -> 354.59 | AN64: Varios, carga, descarga y desperdicio | AO64: gl | AP64: 0.03 | AQ64: 6618.59 | AR64: =+ROUND(AP64*AQ64,2) -> 198.56 | AW64: DESCRIPCION | AX64: UNIDAD | AY64: CANTIDAD | AZ64: PRECIO | BA64: Subtotal | BB64: FLETE
E65: 12.1 | F65: CARPETA DE CEMENTO | G65: m2 | H65: 87.4469 | I65: =+$AR$93 -> 2093.67 | J65: =ROUND(I65*H65,2) -> 183084.95 | L65: =+J65/$K$120 -> 0.00096194437 | M65: =+L65 -> 0.00096194437 | P65: 2.2 - RETIRO DE CARPINTERIAS EXISTENTES | T65: =$G$17 -> Un | U65: =$H$17 -> 2 | X65: 4.2.4 - VIGAS METALICAS - VM1-ESTUDIO | AB65: =$G$31 -> ml | AC65: =$H$31 -> 43.67 | AN65: SUBTOTAL MATERIALES - A - | AR65: =SUM(AR63:AR64) -> 6817.15 | AW65: Materiales: | BD65: DESCRIPCION | BE65: UNIDAD | BF65: CANTIDAD | BG65: PRECIO | BH65: Subtotal | BI65: FLETE
E66: 12.2 | F66: PISO PORCELANATO TIPO 61X61 LIFE TIZA SIN PULIR | G66: m2 | H66: 87.4469 | I66: =+$AR$114 -> 14423.44 | J66: =ROUND(I66*H66,2) -> 1261285.1 | L66: =+J66/$K$120 -> 0.0066269025 | M66: =+L66 -> 0.0066269025 | AF66: 5 - MAMPOSTERIA | AN66: Mano de Obra: | AS66: =+AR63*AS59 -> 1160900.7 | AW66: SPLIT PISO/TECHO 9000 FRIGORÍAS - FRÍO/CALOR | AX66: un | AY66: 1 | AZ66: 308800 | BA66: =+ROUND(AY66*AZ66,2) -> 308800 | BD66: Materiales:
E67: 12.3 | F67: ZOCALO DE PORCELANATO IDEM PISO | G67: ml | H67: 26.2 | I67: =+$AR$134 -> 1764 | J67: =ROUND(I67*H67,2) -> 46216.8 | L67: =+J67/$K$120 -> 0.00024282712 | M67: =+L67 -> 0.00024282712 | P67: DESCRIPCION | Q67: UNIDAD | R67: CANTIDAD | S67: PRECIO | T67: Subtotal | U67: FLETE | X67: DESCRIPCION | Y67: UNIDAD | Z67: CANTIDAD | AA67: PRECIO | AB67: Subtotal | AC67: FLETE | AF67: 5.4 - DINTEL (2 Fe 8mm, concreto) | AJ67: =$G$44 -> ml | AK67: =$H$44 -> 52.8 | AN67: Oficial | AO67: hs | AP67: 1 | AQ67: 1600.8 | AR67: =+ROUND(AP67*AQ67,2) -> 1600.8 | AW67: Varios de conexionado | AX67: gl | AY67: 1 | AZ67: 57815.083 | BA67: =+ROUND(AY67*AZ67,2) -> 57815.08 | BD67: 18.4 - ESCALERA METALICA - RECTA, UN TRAMO C/BARANDA - ESTUDIO | BE67: UN | BF67: 1 | BG67: 344451.41 | BH67: =ROUND((BG67*BF67),2) -> 344451.41 | BJ67: =+BH67*BI63 -> 344451.41
E68: 12.4 | F68: PISO VINILICO esp 2mm en ENTREPISO DE ESTUDIO | G68: m2 | H68: 90.64 | I68: =+$AR$153 -> 11383.8 | J68: =ROUND(I68*H68,2) -> 1031827.6 | L68: =+J68/$K$120 -> 0.0054213128 | M68: =+L68 -> 0.0054213128 | P68: Materiales: | X68: Materiales: | AN68: Ayudante | AO68: hs | AP68: 1 | AQ68: 1354.7 | AR68: =+ROUND(AP68*AQ68,2) -> 1354.7 | AW68: Varios, carga, descarga y desperdicio | AX68: gl | AY68: 0.03 | AZ68: 366615.08 | BA68: =+ROUND(AY68*AZ68,2) -> 10998.45 | BD68: sujeciones,fijaciones,etc | BE68: gl | BF68: 1 | BG68: 24111.599 | BH68: =ROUND((BG68*BF68),2) -> 24111.6
E69: 12.5 | F69: PISO VINILICO SPC 22407 en ESTUDIO (4ºPISO) Y ENTREPISO AG.FOCO | G69: m2 | H69: 198.9 | I69: =+$AR$172 -> 13992.39 | J69: =ROUND(I69*H69,2) -> 2783086.4 | L69: =+J69/$K$120 -> 0.01462258 | M69: =+L69 -> 0.01462258 | T69: =+ROUND(R69*S69,2) -> 0 | X69: 4.2.4 - VIGAS METALICAS - VM1-ESTUDIO | Y69: m | Z69: 1.1 | AA69: 5472.3 | AB69: =+ROUND(Z69*AA69,2) -> 6019.53 | AF69: DESCRIPCION | AG69: UNIDAD | AH69: CANTIDAD | AI69: PRECIO | AJ69: Subtotal | AK69: FLETE | AW69: SUBTOTAL MATERIALES - A - | BA69: =SUM(BA66:BA68) -> 377613.53 | BD69: Varios, carga, descarga y desperdicio | BE69: gl | BF69: 0.03 | BG69: 368563.01 | BH69: =ROUND((BG69*BF69),2) -> 11056.89
E70: 12.6 | F70: ZOCALO PVC en ESTUDIO Y ENTREPISOS | G70: ml | H70: 180.8 | I70: =+$AR$191 -> 2542.68 | J70: =ROUND(I70*H70,2) -> 459716.54 | L70: =+J70/$K$120 -> 0.002415391 | M70: =+L70 -> 0.002415391 | P70: Varios, carga, descarga y desperdicio | Q70: gl | R70: 0.03 | T70: =+ROUND(R70*S70,2) -> 0 | X70: Sujeciones,fijaciones p/apoyos | Y70: gl | Z70: 1 | AA70: 180.5859 | AB70: =+ROUND(Z70*AA70,2) -> 180.59 | AF70: Materiales: | AN70: SUBTOTAL MANO DE OBRA - B - | AR70: =SUM(AR67:AR69) -> 2955.5 | AW70: Mano de Obra: | BD70: SUBTOTAL MATERIALES - A - | BH70: =SUM(BH67:BH69) -> 379619.9
E71: 12.7 | F71: BASE FENOLICO ENTREPISOS | G71: m2 | H71: 165.006 | I71: =+$AR$210 -> 6332.76 | J71: =ROUND(I71*H71,2) -> 1044943.4 | L71: =+J71/$K$120 -> 0.0054902242 | M71: =+L71 -> 0.0054902242 | P71: SUBTOTAL MATERIALES - A - | T71: =SUM(T69:T70) -> 0 | X71: Varios, carga, descarga y desperdicio | Y71: gl | Z71: 0.03 | AA71: 6200.12 | AB71: =+ROUND(Z71*AA71,2) -> 186 | AF71: Cemento | AG71: Kg | AH71: 0.5 | AI71: 26.528938 | AJ71: =+ROUND(AH71*AI71,2) -> 13.26 | AN71: Equipos: | AW71: Oficial | AX71: hs | AY71: 4 | AZ71: 1600.8 | BA71: =+ROUND(AY71*AZ71,2) -> 6403.2 | BD71: Mano de Obra:
E72: 13 | F72: CARPINTERIA | K72: =SUM(J73:J89) -> 13860405 | L72: =+K72/$K$120 -> 0.072823781 | P72: Mano de Obra: | X72: SUBTOTAL MATERIALES - A - | AB72: =SUM(AB69:AB71) -> 6386.12 | AF72: Arena | AG72: m3 | AH72: 0.006 | AI72: 2066.1157 | AJ72: =+ROUND(AH72*AI72,2) -> 12.4 | AN72: FLETE | AO72: KG | AP72: 40 | AQ72: 1.9600688 | AR72: =+ROUND(AP72*AQ72,2) -> 78.4 | AW72: Ayudante | AX72: hs | AY72: 4 | AZ72: 1354.7 | BA72: =+ROUND(AY72*AZ72,2) -> 5418.8 | BD72: Oficial | BE72: hs | BF72: 40 | BG72: 1600.8 | BH72: =+ROUND(BF72*BG72,2) -> 64032
E73: 13.1 | F73: P1 -1,65x2,40 m - LINEA HERRERO - c/aislación acústica | G73: Un | H73: 3 | I73: =+$AR$229 -> 456665.88 | J73: =ROUND(I73*H73,2) -> 1369997.6 | L73: =+J73/$K$120 -> 0.0071980876 | M73: =+L73 -> 0.0071980876 | P73: Oficial | Q73: hs | R73: 1 | S73: 1600.8 | T73: =+ROUND(R73*S73,2) -> 1600.8 | X73: Mano de Obra: | AF73: Hierro | AG73: Kg | AH73: 0.4662 | AI73: 27.236208 | AJ73: =+ROUND(AH73*AI73,2) -> 12.7 | AN73: SUBTOTAL EQUIPOS - C - | AR73: =SUM(AR72:AR72) -> 78.4 | BD73: Ayudante | BE73: hs | BF73: 40 | BG73: 1354.7 | BH73: =+ROUND(BF73*BG73,2) -> 54188
E74: 13.2 | F74: P2 - 0,90x2,40 m - LINEA HERRERO - placa c/melamina blanca | G74: Un | H74: 3 | I74: =+$AR$248 -> 134218.67 | J74: =ROUND(I74*H74,2) -> 402656.01 | L74: =+J74/$K$120 -> 0.0021155899 | M74: =+L74 -> 0.0021155899 | P74: Ayudante | Q74: hs | R74: 1 | S74: 1354.7 | T74: =+ROUND(R74*S74,2) -> 1354.7 | X74: Oficial | Y74: hs | Z74: 0.5 | AA74: 1600.8 | AB74: =+ROUND(Z74*AA74,2) -> 800.4 | AF74: Varios, carga, descarga y desperdicio | AG74: gl | AH74: 0.03 | AI74: 38.36 | AJ74: =+ROUND(AH74*AI74,2) -> 1.15 | AN74: COSTO NETO TOTAL - D - | AP74: (A+B+C) | AR74: =+AR65+AR70+AR73 -> 9851.05 | AW74: SUBTOTAL MANO DE OBRA - B - | BA74: =SUM(BA71:BA73) -> 11822
E75: 13.3 | F75: P3 - 0,90x2,10 m - LINEA HERRERO - c/aislación acústica | G75: Un | H75: 2 | I75: =+$AR$267 -> 231278.64 | J75: =ROUND(I75*H75,2) -> 462557.28 | L75: =+J75/$K$120 -> 0.0024303165 | M75: =+L75 -> 0.0024303165 | X75: Ayudante | Y75: hs | Z75: 0.5 | AA75: 1354.7 | AB75: =+ROUND(Z75*AA75,2) -> 677.35 | AF75: SUBTOTAL MATERIALES - A - | AJ75: =SUM(AJ71:AJ74) -> 39.51 | AW75: Equipos: | BD75: SUBTOTAL MANO DE OBRA - B - | BH75: =SUM(BH72:BH74) -> 118220 | BI75: =+BH75/BH70 -> 0.31141676
E76: 13.4 | F76: P4 - 0,80x2,10 m - LINEA HERRERO - placa c/melamina blanca | G76: Un | H76: 4 | I76: =+$AR$286 -> 129829.22 | J76: =ROUND(I76*H76,2) -> 519316.88 | L76: =+J76/$K$120 -> 0.0027285364 | M76: =+L76 -> 0.0027285364 | P76: SUBTOTAL MANO DE OBRA - B - | T76: =SUM(T73:T75) -> 2955.5 | AF76: Mano de Obra: | AK76: =+AJ71*AK67 -> 700.128 | AN76: 12 - SOLADO Y ZOCALO | AW76: FLETE | AX76: KG | AY76: 120 | AZ76: 1.9600688 | BA76: =+ROUND(AY76*AZ76,2) -> 235.21 | BD76: Equipos:
E77: 13.5 | F77: CERRAMIENTO 1 - (11,93m+4,40m)x2,55m - LINEA HERRERO | G77: Un | H77: 1 | I77: =+$AR$305 -> 1200547.3 | J77: =ROUND(I77*H77,2) -> 1200547.3 | L77: =+J77/$K$120 -> 0.0063077808 | M77: =+L77 -> 0.0063077808 | P77: Equipos: | X77: SUBTOTAL MANO DE OBRA - B - | AB77: =SUM(AB74:AB76) -> 1477.75 | AC77: =+AB77/AB72 -> 0.23140029 | AF77: Oficial | AG77: hs | AH77: 0.1 | AI77: 1600.8 | AJ77: =+ROUND(AH77*AI77,2) -> 160.08 | AN77: 12.1 - CARPETA DE CEMENTO | AR77: =$G$65 -> m2 | AS77: =$H$65 -> 87.4469 | AW77: SUBTOTAL EQUIPOS - C - | BA77: =SUM(BA76:BA76) -> 235.21 | BD77: FLETE | BE77: KG | BF77: 550 | BG77: 1.9600688 | BH77: =+ROUND(BF77*BG77,2) -> 1078.04
E78: 13.6 | F78: CERRAMIENTO 2 - (11,93m+3,40m+4,40m)x2,55m - LINEA HERRERO | G78: Un | H78: 1 | I78: =+$AR$324 -> 1495008.2 | J78: =ROUND(I78*H78,2) -> 1495008.2 | L78: =+J78/$K$120 -> 0.0078549042 | M78: =+L78 -> 0.0078549042 | P78: FLETE | Q78: KG | R78: 110 | S78: 1.9600688 | T78: =+ROUND(R78*S78,2) -> 215.61 | X78: Equipos: | AF78: Ayudante | AG78: hs | AH78: 0.1 | AI78: 1354.7 | AJ78: =+ROUND(AH78*AI78,2) -> 135.47 | AW78: COSTO NETO TOTAL - D - | AY78: (A+B+C) | BA78: =+BA69+BA74+BA77 -> 389670.74 | BD78: SUBTOTAL EQUIPOS - C - | BH78: =SUM(BH77:BH77) -> 1078.04
E79: 13.7 | F79: V1 - 1,40x2,00 m - LINEA HERRERO | G79: Un | H79: 4 | I79: =+$AR$343 -> 336855.05 | J79: =ROUND(I79*H79,2) -> 1347420.2 | L79: =+J79/$K$120 -> 0.0070794638 | M79: =+L79 -> 0.0070794638 | P79: SUBTOTAL EQUIPOS - C - | T79: =SUM(T78:T78) -> 215.61 | X79: FLETE | Y79: KG | Z79: 29.1 | AA79: 1.9600688 | AB79: =+ROUND(Z79*AA79,2) -> 57.04 | AN79: DESCRIPCION | AO79: UNIDAD | AP79: CANTIDAD | AQ79: PRECIO | AR79: Subtotal | AS79: FLETE | BD79: COSTO NETO TOTAL - D - | BF79: (A+B+C) | BH79: =+BH70+BH75+BH78 -> 498917.94
E80: 13.8 | F80: V2 - 2,70x2,00 m - LINEA HERRERO | G80: Un | H80: 2 | I80: =+$AR$362 -> 663511.37 | J80: =ROUND(I80*H80,2) -> 1327022.7 | L80: =+J80/$K$120 -> 0.0069722937 | M80: =+L80 -> 0.0069722937 | P80: COSTO NETO TOTAL - D - | R80: (A+B+C) | T80: =+T71+T76+T79 -> 3171.11 | X80: SUBTOTAL EQUIPOS - C - | AB80: =SUM(AB79:AB79) -> 57.04 | AF80: SUBTOTAL MANO DE OBRA - B - | AJ80: =SUM(AJ77:AJ79) -> 295.55 | AN80: Materiales: | AW80: 17 - PINTURA
E81: 13.9 | F81: BOX 1 - (2,50+2,40+3,75+2,00)x2,10m - LINEA HERRERO | G81: Un | H81: 1 | I81: =+$AR$381 -> 904927.59 | J81: =ROUND(I81*H81,2) -> 904927.59 | L81: =+J81/$K$120 -> 0.0047545688 | M81: =+L81 -> 0.0047545688 | X81: COSTO NETO TOTAL - D - | Z81: (A+B+C) | AB81: =+AB72+AB77+AB80 -> 7920.91 | AF81: Equipos: | AN81: Cemento | AO81: Kg | AP81: 15 | AQ81: 26.528938 | AR81: =+ROUND(AP81*AQ81,2) -> 397.93 | AW81: 17.1 - LATEX PARA INTERIOR | BA81: =$G$107 -> m2 | BB81: =$H$107 -> 1213.8 | BD81: 18 - VARIOS
E82: 13.10 | F82: BOX 2 - (6x1,20+7x2,10)x2,10m - LINEA HERRERO | G82: Un | H82: 1 | I82: =+$AR$400 -> 1501272.2 | J82: =ROUND(I82*H82,2) -> 1501272.2 | L82: =+J82/$K$120 -> 0.0078878158 | M82: =+L82 -> 0.0078878158 | P82: 2 - DEMOLICIONES | AF82: FLETE | AG82: KG | AH82: 9.9662 | AI82: 1.9600688 | AJ82: =+ROUND(AH82*AI82,2) -> 19.53 | AN82: Arena | AO82: m3 | AP82: 0.03 | AQ82: 2066.1157 | AR82: =+ROUND(AP82*AQ82,2) -> 61.98 | BD82: 18.5 - ESCALERA METALICA - RECTA, DOS TRAMOS C/BARANDA - AG.FOCO | BH82: =$G$116 -> UN | BI82: =$H$116 -> 1
E83: 13.11 | F83: FV1 - 5,20x3,00 m - LINEA HERRERO | G83: Un | H83: 1 | I83: =+$AR$419 -> 525278.78 | J83: =ROUND(I83*H83,2) -> 525278.78 | L83: =+J83/$K$120 -> 0.0027598607 | M83: =+L83 -> 0.0027598607 | P83: 2.3 - RETIRO DE PAÑOS VIDRIADOS P/ OFICINAS | T83: =$G$18 -> m2 | U83: =$H$18 -> 23.04 | X83: 4 - ESTRUCTURA RESISTENTE | AF83: SUBTOTAL EQUIPOS - C - | AJ83: =SUM(AJ82:AJ82) -> 19.53 | AN83: Varios, carga, descarga y desperdicio | AO83: gl | AP83: 0.03 | AQ83: 459.91 | AR83: =+ROUND(AP83*AQ83,2) -> 13.8 | AW83: DESCRIPCION | AX83: UNIDAD | AY83: CANTIDAD | AZ83: PRECIO | BA83: Subtotal
E84: 13.12 | F84: FV2 - 4,90x3,00 m - LINEA HERRERO | G84: Un | H84: 1 | I84: =+$AR$438 -> 556516.67 | J84: =ROUND(I84*H84,2) -> 556516.67 | L84: =+J84/$K$120 -> 0.0029239873 | M84: =+L84 -> 0.0029239873 | X84: 4.2.5 - VIGAS METALICAS - VM2-ESTUDIO | AB84: =$G$32 -> ml | AC84: =$H$32 -> 19.36 | AF84: COSTO NETO TOTAL - D - | AH84: (A+B+C) | AJ84: =+AJ75+AJ80+AJ83 -> 354.59 | AN84: SUBTOTAL MATERIALES - A - | AR84: =SUM(AR81:AR83) -> 473.71 | AW84: Materiales: | BD84: DESCRIPCION | BE84: UNIDAD | BF84: CANTIDAD | BG84: PRECIO | BH84: Subtotal | BI84: FLETE
E85: 13.13 | F85: FV3 - 3,70x3,00 m - LINEA HERRERO | G85: Un | H85: 1 | I85: =+$AR$457 -> 365701.21 | J85: =ROUND(I85*H85,2) -> 365701.21 | L85: =+J85/$K$120 -> 0.0019214262 | M85: =+L85 -> 0.0019214262 | P85: DESCRIPCION | Q85: UNIDAD | R85: CANTIDAD | S85: PRECIO | T85: Subtotal | U85: FLETE | AN85: Mano de Obra: | AW85: Fijador p/Pared | AX85: Lt | AY85: 0.15 | AZ85: 1093.4339 | BA85: =+ROUND(AY85*AZ85,2) -> 164.02 | BD85: Materiales:
E86: 13.14 | F86: PF1 - 3,95x3,00 m - LINEA HERRERO | G86: Un | H86: 1 | I86: =+$AR$476 -> 391494.47 | J86: =ROUND(I86*H86,2) -> 391494.47 | L86: =+J86/$K$120 -> 0.0020569462 | M86: =+L86 -> 0.0020569462 | P86: Materiales: | X86: DESCRIPCION | Y86: UNIDAD | Z86: CANTIDAD | AA86: PRECIO | AB86: Subtotal | AC86: FLETE | AF86: 6 - AISLACION | AN86: Oficial | AO86: hs | AP86: 0.6 | AQ86: 1600.8 | AR86: =+ROUND(AP86*AQ86,2) -> 960.48 | AW86: Latex interior | AX86: Lt | AY86: 0.35 | AZ86: 952.34864 | BA86: =+ROUND(AY86*AZ86,2) -> 333.32 | BD86: 18.5 - ESCALERA METALICA - RECTA, DOS TRAMOS C/BARANDA - AG.FOCO | BE86: UN | BF86: 1 | BG86: 941497.89 | BH86: =ROUND((BG86*BF86),2) -> 941497.89 | BJ86: =+BH86*BI82 -> 941497.89
E87: 13.15 | F87: PF2 - 0,30x3,00 m - LINEA HERRERO | G87: Un | H87: 8 | I87: =+$AR$495 -> 145800.29 | J87: =ROUND(I87*H87,2) -> 1166402.3 | L87: =+J87/$K$120 -> 0.00612838 | M87: =+L87 -> 0.00612838 | T87: =+ROUND(R87*S87,2) -> 0 | X87: Materiales: | AF87: 6.1 - ESPUMA DE POLIURETANO INYECTADO BAJO CHAPA ESTUDIO | AJ87: =$G$46 -> m2 | AK87: =$H$46 -> 315 | AN87: Ayudante | AO87: hs | AP87: 0.4 | AQ87: 1354.7 | AR87: =+ROUND(AP87*AQ87,2) -> 541.88 | AW87: Enduído interior | AX87: kg | AY87: 0.3 | AZ87: 417.35 | BA87: =+ROUND(AY87*AZ87,2) -> 125.21 | BD87: sujeciones,fijaciones,etc | BE87: gl | BF87: 1 | BG87: 65904.852 | BH87: =ROUND((BG87*BF87),2) -> 65904.85
E88: 13.16 | F88: PF3 - 5,00x1,00 m - LINEA HERRERO - DVH 3+3-9mm+3+3 | G88: Un | H88: 1 | I88: =+$AR$514 -> 324285.16 | J88: =ROUND(I88*H88,2) -> 324285.16 | L88: =+J88/$K$120 -> 0.0017038226 | M88: =+L88 -> 0.0017038226 | P88: Varios, carga, descarga y desperdicio | Q88: gl | R88: 0.03 | T88: =+ROUND(R88*S88,2) -> 0 | X88: 4.2.5 - VIGAS METALICAS - VM2-ESTUDIO | Y88: m | Z88: 1.1 | AA88: 10944.6 | AB88: =+ROUND(Z88*AA88,2) -> 12039.06 | AW88: Lija | AX88: Un | AY88: 0.1 | AZ88: 123.80165 | BA88: =+ROUND(AY88*AZ88,2) -> 12.38 | BD88: Varios, carga, descarga y desperdicio | BE88: gl | BF88: 0.03 | BG88: 1007402.7 | BH88: =ROUND((BG88*BF88),2) -> 30222.08
M89: =+L89 -> 0 | P89: SUBTOTAL MATERIALES - A - | T89: =SUM(T87:T88) -> 0 | X89: Sujeciones,fijaciones p/apoyos | Y89: gl | Z89: 1 | AA89: 361.1718 | AB89: =+ROUND(Z89*AA89,2) -> 361.17 | AF89: DESCRIPCION | AG89: UNIDAD | AH89: CANTIDAD | AI89: PRECIO | AJ89: Subtotal | AK89: FLETE | AN89: SUBTOTAL MANO DE OBRA - B - | AR89: =SUM(AR86:AR88) -> 1502.36 | AW89: Entonador-120cc | AX89: Un | AY89: 0.2 | AZ89: 769.33884 | BA89: =+ROUND(AY89*AZ89,2) -> 153.87 | BD89: SUBTOTAL MATERIALES - A - | BH89: =SUM(BH86:BH88) -> 1037624.8
E90: 14 | F90: INSTALACION ELECTRICA | K90: =SUM(J92:J99) -> 82887389 | L90: =+K90/$K$120 -> 0.4354976 | P90: Mano de Obra: | X90: Varios, carga, descarga y desperdicio | Y90: gl | Z90: 0.03 | AA90: 12400.23 | AB90: =+ROUND(Z90*AA90,2) -> 372.01 | AF90: Materiales: | AN90: Equipos: | AW90: varios, pinceles, rodillos, etc | AX90: gl | AY90: 0.08 | AZ90: 2188.6364 | BA90: =+ROUND(AY90*AZ90,2) -> 175.09 | BD90: Mano de Obra:
E91: 14.1 | F91: CORRIENTES FUERTES | P91: Oficial | Q91: hs | R91: 0.7 | S91: 1600.8 | T91: =+ROUND(R91*S91,2) -> 1120.56 | X91: SUBTOTAL MATERIALES - A - | AB91: =SUM(AB88:AB90) -> 12772.24 | AF91: ESPUMA DE POLIURETANO INYECTADO BAJO CUBIERTA DE CHAPA EXISTENTE | AG91: M2 | AH91: 1.1 | AI91: 3570.5 | AJ91: =+ROUND(AH91*AI91,2) -> 3927.55 | AN91: FLETE | AO91: KG | AP91: 60 | AQ91: 1.9600688 | AR91: =+ROUND(AP91*AQ91,2) -> 117.6 | AW91: Varios, carga, descarga y desperdicio | AX91: gl | AY91: 0.03 | AZ91: 963.89 | BA91: =+ROUND(AY91*AZ91,2) -> 28.92 | BD91: Oficial | BE91: hs | BF91: 120 | BG91: 1600.8 | BH91: =+ROUND(BF91*BG91,2) -> 192096
E92: 14.1.1 | F92: EXTRACCION DE ARTEFACTOS DE ILUMINACION | G92: Un | H92: 20 | I92: =+$AR$533 -> 2289.91 | J92: =ROUND(I92*H92,2) -> 45798.2 | L92: =+J92/$K$120 -> 0.00024062775 | M92: =+L92 -> 0.00024062775 | P92: Ayudante | Q92: hs | R92: 0.5 | S92: 1354.7 | T92: =+ROUND(R92*S92,2) -> 677.35 | X92: Mano de Obra: | AF92: Varios, carga, descarga y desperdicio | AG92: gl | AH92: 0.03 | AI92: 3927.55 | AJ92: =+ROUND(AH92*AI92,2) -> 117.83 | AN92: SUBTOTAL EQUIPOS - C - | AR92: =SUM(AR91:AR91) -> 117.6 | BA92: =+ROUND(AY92*AZ92,2) -> 0 | BD92: Ayudante | BE92: hs | BF92: 90 | BG92: 1354.7 | BH92: =+ROUND(BF92*BG92,2) -> 121923
E93: 14.1.2 | F93: RETIRO DE INSTALACION EXISTENTE, CAÑOS,CAJAS, CABLES, ETC | G93: Gl | H93: 1 | I93: =+$AR$552 -> 59894.03 | J93: =ROUND(I93*H93,2) -> 59894.03 | L93: =+J93/$K$120 -> 0.00031468848 | M93: =+L93 -> 0.00031468848 | X93: Oficial | Y93: hs | Z93: 0.7 | AA93: 1600.8 | AB93: =+ROUND(Z93*AA93,2) -> 1120.56 | AF93: SUBTOTAL MATERIALES - A - | AJ93: =SUM(AJ91:AJ92) -> 4045.38 | AN93: COSTO NETO TOTAL - D - | AP93: (A+B+C) | AR93: =+AR84+AR89+AR92 -> 2093.67 | AW93: SUBTOTAL MATERIALES - A - | BA93: =SUM(BA85:BA92) -> 992.81
E94: 14.1.3 | F94: INSTALAC CAÑOS, CAJAS, CABLEADO, TABLEROS,LLAVES Y TOMAS, ARTEF. ILUMINAC., ETC | G94: Gl | H94: 1 | I94: =+$AR$586 -> 58031661 | J94: =ROUND(I94*H94,2) -> 58031661 | L94: =+J94/$K$120 -> 0.30490343 | M94: =+L94 -> 0.30490343 | P94: SUBTOTAL MANO DE OBRA - B - | T94: =SUM(T91:T93) -> 1797.91 | X94: Ayudante | Y94: hs | Z94: 0.7 | AA94: 1354.7 | AB94: =+ROUND(Z94*AA94,2) -> 948.29 | AF94: Mano de Obra: | AK94: =+AJ91*AK87 -> 1237178.2 | AW94: Mano de Obra: | BD94: SUBTOTAL MANO DE OBRA - B - | BH94: =SUM(BH91:BH93) -> 314019 | BI94: =+BH94/BH89 -> 0.30263251
E95: 14.2 | F95: CORRIENTES DEBILES | M95: =+L95 -> 0 | P95: Equipos: | AF95: Oficial | AG95: hs | AI95: 1600.8 | AJ95: =+ROUND(AH95*AI95,2) -> 0 | AN95: 12 - SOLADO Y ZOCALO | AW95: Oficial | AX95: hs | AY95: 0.4 | AZ95: 1600.8 | BA95: =+ROUND(AY95*AZ95,2) -> 640.32 | BD95: Equipos:
E96: 14.2.1 | F96: SISTEMA DE DATOS | G96: Gl | H96: 1 | I96: =+$AR$606 -> 8808061.5 | J96: =ROUND(I96*H96,2) -> 8808061.5 | L96: =+J96/$K$120 -> 0.046278327 | M96: =+L96 -> 0.046278327 | P96: FLETE | Q96: KG | R96: 60 | S96: 1.9600688 | T96: =+ROUND(R96*S96,2) -> 117.6 | X96: SUBTOTAL MANO DE OBRA - B - | AB96: =SUM(AB93:AB95) -> 2068.85 | AC96: =+AB96/AB91 -> 0.1619802 | AF96: Ayudante | AG96: hs | AI96: 1354.7 | AJ96: =+ROUND(AH96*AI96,2) -> 0 | AN96: 12.2 - PISO PORCELANATO TIPO 61X61 LIFE TIZA SIN PULIR | AR96: =$G$66 -> m2 | AS96: =$H$66 -> 87.4469 | AW96: Ayudante | AX96: hs | AY96: 0.4 | AZ96: 1354.7 | BA96: =+ROUND(AY96*AZ96,2) -> 541.88 | BD96: FLETE | BE96: KG | BF96: 550 | BG96: 1.9600688 | BH96: =+ROUND(BF96*BG96,2) -> 1078.04
E97: 14.2.2 | F97: SISTEMA DE TE | G97: Gl | H97: 1 | I97: =+$AR$626 -> 4369139.5 | J97: =ROUND(I97*H97,2) -> 4369139.5 | L97: =+J97/$K$120 -> 0.022955842 | M97: =+L97 -> 0.022955842 | P97: SUBTOTAL EQUIPOS - C - | T97: =SUM(T96:T96) -> 117.6 | X97: Equipos: | BD97: SUBTOTAL EQUIPOS - C - | BH97: =SUM(BH96:BH96) -> 1078.04
E98: 14.2.3 | F98: SISTEMA DE CCTV | G98: Gl | H98: 1 | I98: =+$AR$646 -> 3884414 | J98: =ROUND(I98*H98,2) -> 3884414 | L98: =+J98/$K$120 -> 0.020409051 | M98: =+L98 -> 0.020409051 | P98: COSTO NETO TOTAL - D - | R98: (A+B+C) | T98: =+T89+T94+T97 -> 1915.51 | X98: FLETE | Y98: KG | Z98: 57.7 | AA98: 1.9600688 | AB98: =+ROUND(Z98*AA98,2) -> 113.1 | AF98: SUBTOTAL MANO DE OBRA - B - | AJ98: =SUM(AJ95:AJ97) -> 0 | AN98: DESCRIPCION | AO98: UNIDAD | AP98: CANTIDAD | AQ98: PRECIO | AR98: Subtotal | AS98: FLETE | AW98: SUBTOTAL MANO DE OBRA - B - | BA98: =SUM(BA95:BA97) -> 1182.2 | BD98: COSTO NETO TOTAL - D - | BF98: (A+B+C) | BH98: =+BH89+BH94+BH97 -> 1352721.9
E99: 14.2.4 | F99: DETECCIÓN DE INCENDIO | G99: Gl | H99: 1 | I99: =+$AR$666 -> 7688420.6 | J99: =ROUND(I99*H99,2) -> 7688420.6 | L99: =+J99/$K$120 -> 0.040395635 | M99: =+L99 -> 0.040395635 | X99: SUBTOTAL EQUIPOS - C - | AB99: =SUM(AB98:AB98) -> 113.1 | AF99: Equipos: | AN99: Materiales: | AW99: Equipos:
E100: 15 | F100: INSTALACIÓN ELECTROMECÁNICA | K100: =SUM(J101) -> 14126028 | L100: =+K100/$K$120 -> 0.074219387 | P100: 2 - DEMOLICIONES | X100: COSTO NETO TOTAL - D - | Z100: (A+B+C) | AB100: =+AB91+AB96+AB99 -> 14954.19 | AF100: FLETE | AG100: KG | AH100: 40 | AI100: 1.9600688 | AJ100: =+ROUND(AH100*AI100,2) -> 78.4 | AN100: PORCELANATO 61x61 LIFE TIZA SIN PULIR o similar | AO100: m2 | AP100: 1.05 | AQ100: 7084.81 | AR100: =+ROUND(AP100*AQ100,2) -> 7439.05 | AW100: FLETE | AX100: KG | AY100: 1.435 | AZ100: 1.9600688 | BA100: =+ROUND(AY100*AZ100,2) -> 2.81 | BD100: 18 - VARIOS
E101: 15.1 | F101: ASCENSOR | G101: Gl | H101: 1 | I101: =+$BA$21 -> 14126028 | J101: =ROUND(I101*H101,2) -> 14126028 | L101: =+J101/$K$120 -> 0.074219387 | M101: =+L101 -> 0.074219387 | P101: 2.4 - RETIRO DE BARANDAS EXISTENTES EN TERRAZA | T101: =$G$19 -> ml | U101: =$H$19 -> 18.77 | AF101: SUBTOTAL EQUIPOS - C - | AJ101: =SUM(AJ100:AJ100) -> 78.4 | AN101: Pegamento p/porcelanato | AO101: Kg | AP101: 8.8 | AQ101: 253.56667 | AR101: =+ROUND(AP101*AQ101,2) -> 2231.39 | AW101: SUBTOTAL EQUIPOS - C - | BA101: =SUM(BA100:BA100) -> 2.81 | BD101: 18.6 - ESCALERA METALICA - CARACOL - ESTUDIO | BH101: =$G$117 -> UN | BI101: =$H$117 -> 1
...

Sheet PLAN DE TRABAJO
B8: P L A N D E T R A B A J O S Y D E I N V E R S I O N E S
B10: ESTUDIO TV
B11: LOCALIDAD: RESISTENCIA
B12: EMPRESA: I.L.A.G. CONSTRUCCIONES
D14: MONTO | E14: %
B15: No | C15: D E S C R I P C I O N | D15: DEL | E15: 0 | F15: 1 | G15: 2 | H15: 3
D16: ITEM | E16: INC.
B18: =+'PPTO ESTUDIO TV'!BL10 -> 1 | C18: =+'PPTO ESTUDIO TV'!BM10 -> TRABAJOS PREPARATORIOS | D18: =+'PPTO ESTUDIO TV'!BN10 -> 452975.52 | E18: =+'PPTO ESTUDIO TV'!BO10 -> 0.0014978125 | F18: 1 | I18: =SUM(F18:H18) -> 1
B19: =+'PPTO ESTUDIO TV'!BL11 -> 2 | C19: =+'PPTO ESTUDIO TV'!BM11 -> DEMOLICIONES | D19: =+'PPTO ESTUDIO TV'!BN11 -> 622029.59 | E19: =+'PPTO ESTUDIO TV'!BO11 -> 0.0020568081 | F19: 0.95 | G19: 0.05 | H19: 0 | I19: =SUM(F19:H19) -> 1
B20: =+'PPTO ESTUDIO TV'!BL12 -> 3 | C20: =+'PPTO ESTUDIO TV'!BM12 -> MOVIMIENTO DE SUELO | D20: =+'PPTO ESTUDIO TV'!BN12 -> 113182.63 | E20: =+'PPTO ESTUDIO TV'!BO12 -> 0.0003742506 | F20: 0.95 | G20: 0.05 | H20: 0 | I20: =SUM(F20:H20) -> 1
B21: =+'PPTO ESTUDIO TV'!BL13 -> 4 | C21: =+'PPTO ESTUDIO TV'!BM13 -> ESTRUCTURA RESISTENTE | D21: =+'PPTO ESTUDIO TV'!BN13 -> 21249056 | E21: =+'PPTO ESTUDIO TV'!BO13 -> 0.070262299 | F21: 0.95 | G21: 0.05 | H21: 0 | I21: =SUM(F21:H21) -> 1
B22: =+'PPTO ESTUDIO TV'!BL14 -> 5 | C22: =+'PPTO ESTUDIO TV'!BM14 -> MAMPOSTERIA | D22: =+'PPTO ESTUDIO TV'!BN14 -> 2318511.6 | E22: =+'PPTO ESTUDIO TV'!BO14 -> 0.0076664091 | F22: 0.75 | G22: 0.25 | H22: 0 | I22: =SUM(F22:H22) -> 1
B23: =+'PPTO ESTUDIO TV'!BL15 -> 6 | C23: =+'PPTO ESTUDIO TV'!BM15 -> AISLACION | D23: =+'PPTO ESTUDIO TV'!BN15 -> 2548672 | E23: =+'PPTO ESTUDIO TV'!BO15 -> 0.0084274593 | F23: 0.2 | G23: 0.5 | H23: 0.3 | I23: =SUM(F23:H23) -> 1
B24: =+'PPTO ESTUDIO TV'!BL16 -> 7 | C24: =+'PPTO ESTUDIO TV'!BM16 -> REVOQUE | D24: =+'PPTO ESTUDIO TV'!BN16 -> 2406120.7 | E24: =+'PPTO ESTUDIO TV'!BO16 -> 0.0079560982 | F24: 0.2 | G24: 0.5 | H24: 0.3 | I24: =SUM(F24:H24) -> 1
B25: =+'PPTO ESTUDIO TV'!BL17 -> 8 | C25: =+'PPTO ESTUDIO TV'!BM17 -> REVESTIMIENTO | D25: =+'PPTO ESTUDIO TV'!BN17 -> 34097.032 | E25: =+'PPTO ESTUDIO TV'!BO17 -> 0.00011274552 | G25: 0.65 | H25: 0.35 | I25: =SUM(F25:H25) -> 1
B26: =+'PPTO ESTUDIO TV'!BL18 -> 9 | C26: =+'PPTO ESTUDIO TV'!BM18 -> CUBIERTA DE CHº Gº | D26: =+'PPTO ESTUDIO TV'!BN18 -> 1304592.9 | E26: =+'PPTO ESTUDIO TV'!BO18 -> 0.0043137775 | G26: 0.7 | H26: 0.3 | I26: =SUM(F26:H26) -> 1
B27: =+'PPTO ESTUDIO TV'!BL19 -> 10 | C27: =+'PPTO ESTUDIO TV'!BM19 -> TABIQUE DE PLACAS DE YESO | D27: =+'PPTO ESTUDIO TV'!BN19 -> 21201331 | E27: =+'PPTO ESTUDIO TV'!BO19 -> 0.07010449 | G27: 0.6 | H27: 0.4 | I27: =SUM(F27:H27) -> 1
B28: =+'PPTO ESTUDIO TV'!BL20 -> 11 | C28: =+'PPTO ESTUDIO TV'!BM20 -> CIELORRASO | D28: =+'PPTO ESTUDIO TV'!BN20 -> 7141716 | E28: =+'PPTO ESTUDIO TV'!BO20 -> 0.023614856 | G28: 0.6 | H28: 0.4 | I28: =SUM(F28:H28) -> 1
B29: =+'PPTO ESTUDIO TV'!BL21 -> 12 | C29: =+'PPTO ESTUDIO TV'!BM21 -> SOLADO Y ZOCALO | D29: =+'PPTO ESTUDIO TV'!BN21 -> 10821114 | E29: =+'PPTO ESTUDIO TV'!BO21 -> 0.035781181 | G29: 0.65 | H29: 0.35 | I29: =SUM(F29:H29) -> 1
B30: =+'PPTO ESTUDIO TV'!BL22 -> 13 | C30: =+'PPTO ESTUDIO TV'!BM22 -> CARPINTERIA | D30: =+'PPTO ESTUDIO TV'!BN22 -> 22023711 | E30: =+'PPTO ESTUDIO TV'!BO22 -> 0.072823781 | G30: 0.55 | H30: 0.45 | I30: =SUM(F30:H30) -> 1
B31: =+'PPTO ESTUDIO TV'!BL23 -> 14 | C31: =+'PPTO ESTUDIO TV'!BM23 -> INSTALACION ELECTRICA | D31: =+'PPTO ESTUDIO TV'!BN23 -> 1.3170524e+08 | E31: =+'PPTO ESTUDIO TV'!BO23 -> 0.4354976 | F31: 0.2 | G31: 0.4 | H31: 0.4 | I31: =SUM(F31:H31) -> 1
B32: =+'PPTO ESTUDIO TV'!BL24 -> 15 | C32: =+'PPTO ESTUDIO TV'!BM24 -> INSTALACIÓN ELECTROMECÁNICA | D32: =+'PPTO ESTUDIO TV'!BN24 -> 22445777 | E32: =+'PPTO ESTUDIO TV'!BO24 -> 0.074219387 | G32: 0.6 | H32: 0.4 | I32: =SUM(F32:H32) -> 1
B33: =+'PPTO ESTUDIO TV'!BL25 -> 16 | C33: =+'PPTO ESTUDIO TV'!BM25 -> AIRE ACONDICIONADO | D33: =+'PPTO ESTUDIO TV'!BN25 -> 36155129 | E33: =+'PPTO ESTUDIO TV'!BO25 -> 0.11955084 | F33: 0.2 | G33: 0.4 | H33: 0.4 | I33: =SUM(F33:H33) -> 1
B34: =+'PPTO ESTUDIO TV'!BL26 -> 17 | C34: =+'PPTO ESTUDIO TV'!BM26 -> PINTURA | D34: =+'PPTO ESTUDIO TV'!BN26 -> 7335522.6 | E34: =+'PPTO ESTUDIO TV'!BO26 -> 0.024255698 | G34: 0.5 | H34: 0.5 | I34: =SUM(F34:H34) -> 1
B35: =+'PPTO ESTUDIO TV'!BL27 -> 18 | C35: =+'PPTO ESTUDIO TV'!BM27 -> VARIOS | D35: =+'PPTO ESTUDIO TV'!BN27 -> 12545939 | E35: =+'PPTO ESTUDIO TV'!BO27 -> 0.041484504 | F35: 0.3 | G35: 0.3 | H35: 0.4 | I35: =SUM(F35:H35) -> 1
C36: =+'PPTO ESTUDIO TV'!BM28 -> 0 | I36: =SUM(F36:H36) -> 0
A38: =+'PPTO ESTUDIO TV'!K128 -> 3.0242472e+08 | C38: T O T A L | D38: =SUM(D17:D37) -> 3.0242472e+08 | E38: =SUM(E17:E37) -> 1
B40: =B8 -> P L A N D E T R A B A J O S Y D E I N V E R S I O N E S
B41: =B9 -> 0
B42: =B10 -> ESTUDIO TV
B43: =B11 -> LOCALIDAD: RESISTENCIA
B44: =B12 -> EMPRESA: I.L.A.G. CONSTRUCCIONES
E46: %
B47: No | C47: D E S C R I P C I O N | E47: 0 | F47: =+F15 -> 1 | G47: =+G15 -> 2 | H47: =+H15 -> 3
E48: INC.
B51: =B18 -> 1 | C51: =C18 -> TRABAJOS PREPARATORIOS | D51: =+D18 -> 452975.52 | E51: =+E18 -> 0.0014978125 | F51: =F18*$E51 -> 0.0014978125 | G51: =G18*$E51 -> 0 | H51: =H18*$E51 -> 0 | I51: =SUM(F51:H51)-E51 -> 0
B52: =B19 -> 2 | C52: =C19 -> DEMOLICIONES | D52: =+D19 -> 622029.59 | E52: =+E19 -> 0.0020568081 | F52: =F19*$E52 -> 0.0019539677 | G52: =G19*$E52 -> 0.0001028404 | H52: =H19*$E52 -> 0 | I52: =SUM(F52:H52)-E52 -> 0
B53: =B20 -> 3 | C53: =C20 -> MOVIMIENTO DE SUELO | D53: =+D20 -> 113182.63 | E53: =+E20 -> 0.0003742506 | F53: =F20*$E53 -> 0.00035553807 | G53: =G20*$E53 -> 1.871253e-05 | H53: =H20*$E53 -> 0 | I53: =SUM(F53:H53)-E53 -> 0
B54: =B21 -> 4 | C54: =C21 -> ESTRUCTURA RESISTENTE | D54: =+D21 -> 21249056 | E54: =+E21 -> 0.070262299 | F54: =F21*$E54 -> 0.066749184 | G54: =G21*$E54 -> 0.003513115 | H54: =H21*$E54 -> 0 | I54: =SUM(F54:H54)-E54 -> 0
B55: =B22 -> 5 | C55: =C22 -> MAMPOSTERIA | D55: =+D22 -> 2318511.6 | E55: =+E22 -> 0.0076664091 | F55: =F22*$E55 -> 0.0057498068 | G55: =G22*$E55 -> 0.0019166023 | H55: =H22*$E55 -> 0 | I55: =SUM(F55:H55)-E55 -> 0
B56: =B23 -> 6 | C56: =C23 -> AISLACION | D56: =+D23 -> 2548672 | E56: =+E23 -> 0.0084274593 | F56: =F23*$E56 -> 0.0016854919 | G56: =G23*$E56 -> 0.0042137297 | H56: =H23*$E56 -> 0.0025282378 | I56: =SUM(F56:H56)-E56 -> 0
B57: =B24 -> 7 | C57: =C24 -> REVOQUE | D57: =+D24 -> 2406120.7 | E57: =+E24 -> 0.0079560982 | F57: =F24*$E57 -> 0.0015912196 | G57: =G24*$E57 -> 0.0039780491 | H57: =H24*$E57 -> 0.0023868295 | I57: =SUM(F57:H57)-E57 -> 0
B58: =B25 -> 8 | C58: =C25 -> REVESTIMIENTO | D58: =+D25 -> 34097.032 | E58: =+E25 -> 0.00011274552 | F58: =F25*$E58 -> 0 | G58: =G25*$E58 -> 7.3284589e-05 | H58: =H25*$E58 -> 3.9460933e-05 | I58: =SUM(F58:H58)-E58 -> 0
B59: =B26 -> 9 | C59: =C26 -> CUBIERTA DE CHº Gº | D59: =+D26 -> 1304592.9 | E59: =+E26 -> 0.0043137775 | F59: =F26*$E59 -> 0 | G59: =G26*$E59 -> 0.0030196442 | H59: =H26*$E59 -> 0.0012941332 | I59: =SUM(F59:H59)-E59 -> 0
B60: =B27 -> 10 | C60: =C27 -> TABIQUE DE PLACAS DE YESO | D60: =+D27 -> 21201331 | E60: =+E27 -> 0.07010449 | F60: =F27*$E60 -> 0 | G60: =G27*$E60 -> 0.042062694 | H60: =H27*$E60 -> 0.028041796 | I60: =SUM(F60:H60)-E60 -> 0
B61: =B28 -> 11 | C61: =C28 -> CIELORRASO | D61: =+D28 -> 7141716 | E61: =+E28 -> 0.023614856 | F61: =F28*$E61 -> 0 | G61: =G28*$E61 -> 0.014168913 | H61: =H28*$E61 -> 0.0094459423 | I61: =SUM(F61:H61)-E61 -> 0
B62: =B29 -> 12 | C62: =C29 -> SOLADO Y ZOCALO | D62: =+D29 -> 10821114 | E62: =+E29 -> 0.035781181 | F62: =F29*$E62 -> 0 | G62: =G29*$E62 -> 0.023257768 | H62: =H29*$E62 -> 0.012523414 | I62: =SUM(F62:H62)-E62 -> 0
... B68: =B35 -> 18 | C68: =C35 -> VARIOS | D68: =+D35 -> 12545939 | E68: =+E35 -> 0.041484504 | F68: =F35*$E68 -> 0.012445351 | G68: =G35*$E68 -> 0.012445351 | H68: =H35*$E68 -> 0.016593801 | I68: =SUM(F68:H68)-E68 -> 0
B69: =B36 -> 0
B70: =B37 -> 0
C73: TOTAL | D73: =SUM(D51:D72) -> 3.0242472e+08 | E73: =SUM(E51:E72) -> 1
C74: % AVANCE FISICO | D74: MENSUAL | E74: 0 | F74: =SUM(F49:F72) -> 0.20303806 | G74: =SUM(G49:G72) -> 0.42750264 | H74: =SUM(H49:H72) -> 0.3694593 | I74: =SUM(F74:H74) -> 1
D75: ACUMULADO | E75: 0 | F75: =+F74+E75 -> 0.20303806 | G75: =+G74+F75 -> 0.6305407 | H75: =+H74+G75 -> 1
C76: INVERSION EN | D76: MENSUAL | E76: 0 | F76: =+F74*$D$73 -> 61403728 | G76: =+G74*$D$73 -> 1.2928737e+08 | H76: =+H74*$D$73 -> 1.1173362e+08
C77: PESOS | D77: ACUMULADO | E77: 0 | F77: =+F76 -> 61403728 | G77: =+G76+F77 -> 1.9069109e+08 | H77: =+H76+G77 -> 3.0242472e+08 | I77: =H77-$D$73 -> 0
E80: 0 | F80: =F47 -> 1 | G80: =G47 -> 2 | H80: =H47 -> 3
E81: 0 | F81: =F75 -> 0.20303806 | G81: =G75 -> 0.6305407 | H81: =H75 -> 1
E82: 0 | F82: =F77 -> 61403728 | G82: =G77 -> 1.9069109e+08 | H82: =H77 -> 3.0242472e+08
